Workbook

Sheet Resumen
A1: CODE CELLS™ — Resumen del modelo a 12 y 24 meses
A2: MXN sin IVA. Todo se calcula desde la hoja Supuestos. Estimaciones: medir y corregir con el piloto.
A4: Resultado | B4: Conservador | C4: Base | D4: Optimista | E4: Cómo leerlo
A5: Médicos activos al mes 12 (nov-2027) | B5: ='Conservador'!N20 | C5: ='Base'!N20 | D5: ='Optimista'!N20
A6: Médicos activos al mes 24 (nov-2028) | B6: ='Conservador'!Z20 | C6: ='Base'!Z20 | D6: ='Optimista'!Z20
A7: de ellos fundadores | B7: ='Conservador'!Z14 | C7: ='Base'!Z14 | D7: ='Optimista'!Z14 | E7: Los fundadores pagan el precio congelado.
A8: de ellos por el canal Regene | B8: ='Conservador'!Z19 | C8: ='Base'!Z19 | D8: ='Optimista'!Z19 | E8: Clínico con descuento/comisión del canal.
A9: GB guardados al mes 24 | B9: ='Conservador'!Z30 | C9: ='Base'!Z30 | D9: ='Optimista'!Z30 | E9: Se acumulan: la NOM-004 obliga a conservar 5 años aunque el médico se vaya.
A10: Ingreso por almacenamiento adicional, mes 24 | B10: ='Conservador'!Z31 | C10: ='Base'!Z31 | D10: ='Optimista'!Z31
A11: Costo de almacenamiento (2 copias), mes 24 | B11: ='Conservador'!Z39 | C11: ='Base'!Z39 | D11: ='Optimista'!Z39
A12: Ingreso recurrente mensual (MRR) mes 12 | B12: ='Conservador'!N32 | C12: ='Base'!N32 | D12: ='Optimista'!N32
A13: Ingreso recurrente mensual (MRR) mes 24 | B13: ='Conservador'!Z32 | C13: ='Base'!Z32 | D13: ='Optimista'!Z32
A14: Ingreso recurrente anualizado (ARR) mes 24 | B14: ='Conservador'!Z61 | C14: ='Base'!Z61 | D14: ='Optimista'!Z61 | E14: MRR × 12.
A15: Ingreso total acumulado 24 meses | B15: =SUM('Conservador'!C35:Z35) | C15: =SUM('Base'!C35:Z35) | D15: =SUM('Optimista'!C35:Z35)
A16: Margen de contribución mes 24 | B16: ='Conservador'!Z46 | C16: ='Base'!Z46 | D16: ='Optimista'!Z46 | E16: Lo que queda de cada peso tras IA, cobro, soporte y migraciones.
A17: Flujo acumulado al mes 12 | B17: ='Conservador'!N60 | C17: ='Base'!N60 | D17: ='Optimista'!N60
A18: Flujo acumulado al mes 24 | B18: ='Conservador'!Z60 | C18: ='Base'!Z60 | D18: ='Optimista'!Z60 | E18: Negativo = todavía no recupera lo invertido.
A19: Capital requerido (peor punto del flujo acumulado) | B19: =MAX(0,-MIN('Conservador'!C60:Z60)) | C19: =MAX(0,-MIN('Base'!C60:Z60)) | D19: =MAX(0,-MIN('Optimista'!C60:Z60)) | E19: El dinero que hay que tener para no quedarse sin caja.
A20: Primer mes con flujo positivo (# de mes) | B20: =MIN('Conservador'!C62:Z62) | C20: =MIN('Base'!C62:Z62) | D20: =MIN('Optimista'!C62:Z62) | E20: 99 = no ocurre en 24 meses. Mes 1 = dic-2026.
A22: Economía por médico al mes (estado estable) | B22: Red | C22: Clínico | D22: Fundador*
A23: Ingreso sin IVA | B23: =Supuestos!$B$5/(1+Supuestos!$B$10) | C23: =Supuestos!$B$6/(1+Supuestos!$B$10) | D23: =Supuestos!$B$8/(1+Supuestos!$B$10)
A24: IA (NOVA) | B24: =Supuestos!$B$17*Supuestos!$B$14 | C24: =Supuestos!$B$18*Supuestos!$B$14 | D24: =C24
A25: Comisión de cobro + factura | B25: =(Supuestos!$B$32+Supuestos!$B$5*Supuestos!$B$31)*(1+Supuestos!$B$10)+Supuestos!$B$33 | C25: =(Supuestos!$B$32+Supuestos!$B$6*Supuestos!$B$31)*(1+Supuestos!$B$10)+Supuestos!$B$33 | D25: =(Supuestos!$B$32+Supuestos!$B$8*Supuestos!$B$31)*(1+Supuestos!$B$10)+Supuestos!$B$33
A26: Soporte | B26: =Supuestos!$B$37*Supuestos!$B$38 | C26: =Supuestos!$B$37*Supuestos!$B$38 | D26: =Supuestos!$B$37*Supuestos!$B$38
A27: Contribución por médico | B27: =B23-B24-B25-B26 | C27: =C23-C24-C25-C26 | D27: =D23-D24-D25-D26
A28: Contribución % | B28: =IF(B23=0,0,B27/B23) | C28: =IF(C23=0,0,C27/C23) | D28: =IF(D23=0,0,D27/D23)
A29: * Fundador ya con portal clínico (después del lanzamiento).
A31: Punto de equilibrio
A32: Costos fijos mensuales tras el lanzamiento (infra + contador + sueldo) | B32: =(Supuestos!$B$15+Supuestos!$B$16)*Supuestos!$B$14+Supuestos!$B$36+Supuestos!$B$40
A33: Médicos Clínico necesarios para cubrir los fijos | B33: =IF(C27<=0,"No se cubre",ROUNDUP(B32/C27,0)) | E33: Sin contar adquisición ni pagos únicos.
A34: Médicos fundadores necesarios para cubrir los fijos | B34: =IF(D27<=0,"No se cubre",ROUNDUP(B32/D27,0))
A35: Médicos Clínico necesarios para pagarte un sueldo de | B35: 40000 | C35: =IF(C27<=0,"No se cubre",ROUNDUP((B32-Supuestos!$B$40+B35)/C27,0)) | E35: Cambia el monto en azul. Resultado en la columna C.

Sheet Supuestos
A1: CODE CELLS™ — Modelo financiero 24 meses (dic-2026 a nov-2028)
A2: Cómo usarlo: cambia solo las celdas en AZUL (las amarillas son las decisiones clave). Todo lo demás se calcula. Montos en MXN salvo que diga USD. Generado 2026-10-19.
A4: Precios (MXN, con IVA) | E4: Fuente / nota
A5: Precio plan Red (mensual) | B5: 600 | E5: Dato de Víctor 2026-10-19. Directorio + solicitudes de cita.
A6: Precio plan Clínico (mensual, incluye todo) | B6: 1100 | E6: Dato de Víctor 2026-10-19. Red + portal clínico + NOVA + app del paciente.
A7: Precio fundador mientras solo existe Red (mensual) | B7: 600 | E7: Propuesta: el fundador paga lo mismo que Red mientras el portal clínico no existe.
A8: Precio fundador con portal clínico (mensual) | B8: 800 | E8: Propuesta: al lanzarse el Clínico el fundador lo recibe a este precio congelado 24 meses (36 los primeros 25), contra 1 100 de lista. A 600 su contribución cae a ~147 MXN (28%). En 24 meses ningún fundador sale del precio congelado.
A9: Lugares de fundador | B9: 100 | E9: Oferta de 100 médicos fundadores.
A10: IVA | B10: 0.16 | E10: Los ingresos del modelo se calculan SIN IVA (el IVA se entera al SAT).
A11: Precio de migración por paciente (con IVA) | B11: 58 | E11: Propuesta (Víctor decidió que la migración se cobra aparte): ~50 + IVA por paciente. Costo estimado ~32 por paciente (ver bloque Migración).
A13: Tipo de cambio y costos en USD | E13: Fuente / nota
A14: Tipo de cambio MXN por USD | B14: 18.49 | E14: FIX Banxico 16-oct-2026 (18.4930). Prueba con 21 para ver el efecto de una devaluación.
A15: Infraestructura actual (USD/mes) | B15: 68.33 | E15: Dato de Víctor: Airtable 20 + Vercel 20 + API Anthropic 20 + dominio 100/año.
A16: Infraestructura nueva desde el lanzamiento Clínico (USD/mes) | B16: 80 | E16: Estimado: PostgreSQL ~25, respaldos, monitoreo 0–26, correo 0–20, Cloudflare R2. Ver docs/VALUACION-2026-10-19.md §4.
A17: IA por médico en plan Red (USD/mes) | B17: 0.5 | E17: Estimado: el directorio casi no usa NOVA.
A18: IA por médico en plan Clínico (USD/mes) | B18: 14.1 | E18: Estimado con caché de instrucciones: mezcla 30% bajo (4) / 50% medio (13) / 20% alto (32). SIN caché se duplica (~28). Tope de NOVA por paciente (decisión de Víctor).
A20: Almacenamiento de archivos (por GB) | E20: Fuente / nota
A21: GB incluidos en el plan Clínico | B21: 20 | E21: Propuesta. Ejemplo de Víctor: 4–6 fotos pre/post (~4 MB c/u) + consentimientos ≈ 26 MB por paciente quirúrgico → 100 pacientes al año ≈ 2.6 GB.
A22: GB incluidos en el plan Red | B22: 1 | E22: Propuesta: solo fotos de perfil y documentos del directorio.
A23: Precio por GB adicional al mes (con IVA) | B23: 2 | E23: Propuesta. Para volúmenes de TB (imagenología) ofrecer paquete, p. ej. 1 TB por ~$990/mes (costo ~$410).
A24: GB nuevos por médico Clínico al mes (promedio) | B24: 0.5 | E24: Estimado: mezcla de especialidades. Muy variable: de MB a TB según la especialidad.
A25: % de médicos que superan lo incluido | B25: 0.1 | E25: Estimado: cirugía plástica, dermatología, imagen, oftalmología.
A26: GB adicionales promedio de esos médicos | B26: 100 | E26: Estimado. Un médico de imagenología puede llegar a TB: cotizar paquete.
A27: Costo por GB al mes, copia principal (USD) | B27: 0.015 | E27: Verificado: Cloudflare R2 0.015 USD/GB, sin cargo por descarga.
A28: Costo por GB al mes, copia de respaldo (USD) | B28: 0.00695 | E28: Secundario: Backblaze B2 ~6.95 USD/TB. Respaldo en otro proveedor.
A30: Cobro | E30: Fuente / nota
A31: Comisión de la pasarela (% del cobro) | B31: 0.036 | E31: Secundario: Stripe México ~3.6% + 3 MXN por tarjeta nacional. Se suma IVA sobre la comisión.
A32: Comisión fija por cobro (MXN) | B32: 3 | E32: Secundario (Stripe).
A33: Timbrado CFDI por factura (MXN) | B33: 2 | E33: Secundario: 0.50–2 MXN por folio según el PAC.
A35: Operación | E35: Fuente / nota
A36: Contador (MXN/mes) | B36: 2500 | E36: COTIZAR. Valor de ejemplo.
A37: Horas de soporte por médico al mes | B37: 0.5 | E37: Estimado.
A38: Costo por hora de soporte (MXN) | B38: 150 | E38: Estimado (asistente de soporte).
A39: Costo de adquisición por médico nuevo (MXN) | B39: 1500 | E39: Estimado: publicidad, visitas, demo. Medirlo en el piloto.
A40: Sueldo de Víctor (MXN/mes) | B40: 0 | E40: Decisión: en 0 el modelo muestra el flujo sin pagar tu tiempo. Ponle un monto para ver cuándo se sostiene pagándote.
A41: Abogado (pago único, mes 1) | B41: 40000 | E41: COTIZAR: aviso de privacidad clínico, contrato de afiliación, términos.
A42: Prueba de penetración (pago único, mes de lanzamiento Clínico) | B42: 50000 | E42: COTIZAR.
A43: Mes de lanzamiento del plan Clínico (1 = dic-2026) | B43: 6 | E43: Supuesto: mayo-2027, tras acta constitutiva + IMPI + abogado.
A45: Migración de expedientes (costo de producirla) | E45: Fuente / nota
A46: Pacientes promedio por migración | B46: 200 | E46: Estimado.
A47: Páginas por paciente | B47: 10 | E47: Estimado.
A48: IA por página (USD) | B48: 0.013 | E48: Estimado (lectura de imagen con Claude Sonnet 5; la mitad en modo por lotes).
A49: Minutos de revisión humana por página | B49: 1.5 | E49: Estimado: verificar identidad y valores (no se inventa nada).
A50: Sueldo mensual por persona de migración (MXN, con cargas) | B50: 18000 | E50: Decisión de Víctor: se contrata personal. Monto COTIZAR.
A51: Horas productivas al mes por persona | B51: 140 | E51: Estimado.
A52: Meses de anticipación para contratar y capacitar antes de Regene | B52: 2 | E52: La primera persona entra este número de meses antes del canal Regene.
A53: Capacitación inicial (pago único al contratar) | B53: 15000 | E53: Estimado: NOM-004, LFPDPPP, identidad, uso del sistema. COTIZAR.
A55: Canal Regene Global | E55: Fuente / nota
A56: Médicos afiliados a Regene Global | B56: 2500 | E56: Dato de Víctor 2026-10-19 (aproximado).
A57: Mes en que arranca el canal Regene (1 = dic-2026) | B57: 13 | E57: Decisión de Víctor: primero arrancamos solos; Regene entra cuando haya infraestructura para 1 000 médicos y personal de migración capacitado. Supuesto: dic-2027 (el trabajo técnico pendiente es de 285–580 h).
A58: Descuento o comisión para el canal Regene | B58: 0 | E58: Dato de Víctor: Regene no cobra, solo refiere a los médicos. Precio de lista.
A59: Infraestructura para 1 000 médicos (USD/mes, desde el mes previo a Regene) | B59: 150 | E59: Estimado: base de datos y almacenamiento dimensionados para 1 000 médicos. Cotizar.
A60: Costo de incorporar a un médico Regene (MXN) | B60: 300 | E60: Estimado: alta, capacitación grupal. Menor que el costo de adquisición normal.
A61: Infraestructura adicional por cada 100 médicos (USD/mes) | B61: 25 | E61: Estimado: base de datos y cómputo más grandes al crecer.
A63: Escenarios | B63: Conservador | C63: Base | D63: Optimista | E63: Fuente / nota
A64: Médicos nuevos por mes | B64: 3 | C64: 6 | D64: 10 | E64: Estimado. El piloto de diciembre es de 5–10 médicos.
A65: Cancelación mensual | B65: 0.04 | C65: 0.03 | D65: 0.02 | E65: Estimado. SaaS para médicos pequeños: 2–5% mensual es un rango común.
A66: % de médicos nuevos (no fundadores) que eligen Clínico tras el lanzamiento | B66: 0.4 | C66: 0.5 | D66: 0.6 | E66: Estimado.
A67: % de médicos Red que suben a Clínico cada mes tras el lanzamiento | B67: 0.03 | C67: 0.05 | D67: 0.08 | E67: Estimado.
A68: % de médicos que entran a Clínico y compran migración | B68: 0.2 | C68: 0.3 | D68: 0.4 | E68: Estimado.
A69: % de médicos Regene que se afilian (repartido del mes de arranque al mes 24) | B69: 0.05 | C69: 0.1 | D69: 0.2 | E69: Estimado. 5% = 125 médicos; 20% = 500.

Sheet Conservador
A1: Escenario Conservador — mes a mes (MXN sin IVA)
A3: Mes # | C3: 1 | D3: 2 | E3: 3 | F3: 4 | G3: 5 | H3: 6 | I3: 7 | J3: 8 | K3: 9 | L3: 10 | M3: 11 | N3: 12 | O3: 13 | P3: 14 | Q3: 15 | R3: 16 | S3: 17 | T3: 18 | U3: 19 | V3: 20 | W3: 21 | X3: 22 | Y3: 23 | Z3: 24
A4: Mes | C4: dic-2026 | D4: ene-2027 | E4: feb-2027 | F4: mar-2027 | G4: abr-2027 | H4: may-2027 | I4: jun-2027 | J4: jul-2027 | K4: ago-2027 | L4: sep-2027 | M4: oct-2027 | N4: nov-2027 | O4: dic-2027 | P4: ene-2028 | Q4: feb-2028 | R4: mar-2028 | S4: abr-2028 | T4: may-2028 | U4: jun-2028 | V4: jul-2028 | W4: ago-2028 | X4: sep-2028 | Y4: oct-2028 | Z4: nov-2028
A5: Plan Clínico disponible (1 = sí) | C5: =IF(C3>=Supuestos!$B$43,1,0) | D5: =IF(D3>=Supuestos!$B$43,1,0) | E5: =IF(E3>=Supuestos!$B$43,1,0) | F5: =IF(F3>=Supuestos!$B$43,1,0) | G5: =IF(G3>=Supuestos!$B$43,1,0) | H5: =IF(H3>=Supuestos!$B$43,1,0) | I5: =IF(I3>=Supuestos!$B$43,1,0) | J5: =IF(J3>=Supuestos!$B$43,1,0) | ... Z5: =IF(Z3>=Supuestos!$B$43,1,0)
A7: MÉDICOS
A8: Médicos nuevos | C8: =Supuestos!$B$64 | D8: =Supuestos!$B$64 | E8: =Supuestos!$B$64 | F8: =Supuestos!$B$64 | G8: =Supuestos!$B$64 | H8: =Supuestos!$B$64 | I8: =Supuestos!$B$64 | J8: =Supuestos!$B$64 | ... Z8: =Supuestos!$B$64
A9: Fundadores nuevos | C9: =MIN(C8,Supuestos!$B$9) | D9: =MIN(D8,Supuestos!$B$9-C10) | E9: =MIN(E8,Supuestos!$B$9-D10) | F9: =MIN(F8,Supuestos!$B$9-E10) | G9: =MIN(G8,Supuestos!$B$9-F10) | H9: =MIN(H8,Supuestos!$B$9-G10) | I9: =MIN(I8,Supuestos!$B$9-H10) | J9: =MIN(J8,Supuestos!$B$9-I10) | K9: =MIN(K8,Supuestos!$B$9-J10) | ... Z9: =MIN(Z8,Supuestos!$B$9-Y10)
A10: Fundadores inscritos (acumulado) | C10: =C9 | D10: =C10+D9 | E10: =D10+E9 | F10: =E10+F9 | G10: =F10+G9 | H10: =G10+H9 | I10: =H10+I9 | J10: =I10+J9 | K10: =J10+K9 | ... Z10: =Y10+Z9
A11: Nuevos no fundadores | C11: =C8-C9 | D11: =D8-D9 | E11: =E8-E9 | F11: =F8-F9 | G11: =G8-G9 | H11: =H8-H9 | I11: =I8-I9 | J11: =J8-J9 | ... Z11: =Z8-Z9
A12: Nuevos que eligen Clínico | C12: =C11*C5*Supuestos!$B$66 | D12: =D11*D5*Supuestos!$B$66 | E12: =E11*E5*Supuestos!$B$66 | F12: =F11*F5*Supuestos!$B$66 | G12: =G11*G5*Supuestos!$B$66 | H12: =H11*H5*Supuestos!$B$66 | I12: =I11*I5*Supuestos!$B$66 | J12: =J11*J5*Supuestos!$B$66 | ... Z12: =Z11*Z5*Supuestos!$B$66
A13: Nuevos que eligen Red | C13: =C11-C12 | D13: =D11-D12 | E13: =E11-E12 | F13: =F11-F12 | G13: =G11-G12 | H13: =H11-H12 | I13: =I11-I12 | J13: =J11-J12 | ... Z13: =Z11-Z12
A14: Fundadores activos | C14: =C9 | D14: =C14*(1-Supuestos!$B$65)+D9 | E14: =D14*(1-Supuestos!$B$65)+E9 | F14: =E14*(1-Supuestos!$B$65)+F9 | G14: =F14*(1-Supuestos!$B$65)+G9 | H14: =G14*(1-Supuestos!$B$65)+H9 | I14: =H14*(1-Supuestos!$B$65)+I9 | J14: =I14*(1-Supuestos!$B$65)+J9 | K14: =J14*(1-Supuestos!$B$65)+K9 | ... Z14: =Y14*(1-Supuestos!$B$65)+Z9
A15: Suben de Red a Clínico | C15: =0 | D15: =C16*(1-Supuestos!$B$65)*D5*Supuestos!$B$67 | E15: =D16*(1-Supuestos!$B$65)*E5*Supuestos!$B$67 | F15: =E16*(1-Supuestos!$B$65)*F5*Supuestos!$B$67 | G15: =F16*(1-Supuestos!$B$65)*G5*Supuestos!$B$67 | H15: =G16*(1-Supuestos!$B$65)*H5*Supuestos!$B$67 | I15: =H16*(1-Supuestos!$B$65)*I5*Supuestos!$B$67 | J15: =I16*(1-Supuestos!$B$65)*J5*Supuestos!$B$67 | K15: =J16*(1-Supuestos!$B$65)*K5*Supuestos!$B$67 | ... Z15: =Y16*(1-Supuestos!$B$65)*Z5*Supuestos!$B$67
A16: Red activos | C16: =C13 | D16: =C16*(1-Supuestos!$B$65)-D15+D13 | E16: =D16*(1-Supuestos!$B$65)-E15+E13 | F16: =E16*(1-Supuestos!$B$65)-F15+F13 | G16: =F16*(1-Supuestos!$B$65)-G15+G13 | H16: =G16*(1-Supuestos!$B$65)-H15+H13 | I16: =H16*(1-Supuestos!$B$65)-I15+I13 | J16: =I16*(1-Supuestos!$B$65)-J15+J13 | K16: =J16*(1-Supuestos!$B$65)-K15+K13 | ... Z16: =Y16*(1-Supuestos!$B$65)-Z15+Z13
A17: Clínico activos (precio completo) | C17: =C12 | D17: =C17*(1-Supuestos!$B$65)+D12+D15 | E17: =D17*(1-Supuestos!$B$65)+E12+E15 | F17: =E17*(1-Supuestos!$B$65)+F12+F15 | G17: =F17*(1-Supuestos!$B$65)+G12+G15 | H17: =G17*(1-Supuestos!$B$65)+H12+H15 | I17: =H17*(1-Supuestos!$B$65)+I12+I15 | J17: =I17*(1-Supuestos!$B$65)+J12+J15 | K17: =J17*(1-Supuestos!$B$65)+K12+K15 | ... Z17: =Y17*(1-Supuestos!$B$65)+Z12+Z15
A18: Médicos Regene nuevos | C18: =IF(C3>=Supuestos!$B$57,Supuestos!$B$56*Supuestos!$B$69/MAX(1,25-Supuestos!$B$57),0) | D18: =IF(D3>=Supuestos!$B$57,Supuestos!$B$56*Supuestos!$B$69/MAX(1,25-Supuestos!$B$57),0) | E18: =IF(E3>=Supuestos!$B$57,Supuestos!$B$56*Supuestos!$B$69/MAX(1,25-Supuestos!$B$57),0) | F18: =IF(F3>=Supuestos!$B$57,Supuestos!$B$56*Supuestos!$B$69/MAX(1,25-Supuestos!$B$57),0) | G18: =IF(G3>=Supuestos!$B$57,Supuestos!$B$56*Supuestos!$B$69/MAX(1,25-Supuestos!$B$57),0) | H18: =IF(H3>=Supuestos!$B$57,Supuestos!$B$56*Supuestos!$B$69/MAX(1,25-Supuestos!$B$57),0) | I18: =IF(I3>=Supuestos!$B$57,Supuestos!$B$56*Supuestos!$B$69/MAX(1,25-Supuestos!$B$57),0) | J18: =IF(J3>=Supuestos!$B$57,Supuestos!$B$56*Supuestos!$B$69/MAX(1,25-Supuestos!$B$57),0) | ... Z18: =IF(Z3>=Supuestos!$B$57,Supuestos!$B$56*Supuestos!$B$69/MAX(1,25-Supuestos!$B$57),0)
A19: Médicos Regene activos (Clínico con descuento) | C19: =C18 | D19: =C19*(1-Supuestos!$B$65)+D18 | E19: =D19*(1-Supuestos!$B$65)+E18 | F19: =E19*(1-Supuestos!$B$65)+F18 | G19: =F19*(1-Supuestos!$B$65)+G18 | H19: =G19*(1-Supuestos!$B$65)+H18 | I19: =H19*(1-Supuestos!$B$65)+I18 | J19: =I19*(1-Supuestos!$B$65)+J18 | K19: =J19*(1-Supuestos!$B$65)+K18 | ... Z19: =Y19*(1-Supuestos!$B$65)+Z18
A20: Total médicos activos | C20: =C14+C16+C17+C19 | D20: =D14+D16+D17+D19 | E20: =E14+E16+E17+E19 | F20: =F14+F16+F17+F19 | G20: =G14+G16+G17+G19 | H20: =H14+H16+H17+H19 | I20: =I14+I16+I17+I19 | J20: =J14+J16+J17+J19 | ... Z20: =Z14+Z16+Z17+Z19
A21: Médicos usando el portal clínico | C21: =C17+C19+C14*C5 | D21: =D17+D19+D14*D5 | E21: =E17+E19+E14*E5 | F21: =F17+F19+F14*F5 | G21: =G17+G19+G14*G5 | H21: =H17+H19+H14*H5 | I21: =I17+I19+I14*I5 | J21: =J17+J19+J14*J5 | ... Z21: =Z17+Z19+Z14*Z5
A22: Médicos usando solo Red | C22: =C20-C21 | D22: =D20-D21 | E22: =E20-E21 | F22: =F20-F21 | G22: =G20-G21 | H22: =H20-H21 | I22: =I20-I21 | J22: =J20-J21 | ... Z22: =Z20-Z21
A24: INGRESOS
A25: Fundadores | C25: =C14*IF(C5=1,Supuestos!$B$8,Supuestos!$B$7)/(1+Supuestos!$B$10) | D25: =D14*IF(D5=1,Supuestos!$B$8,Supuestos!$B$7)/(1+Supuestos!$B$10) | E25: =E14*IF(E5=1,Supuestos!$B$8,Supuestos!$B$7)/(1+Supuestos!$B$10) | F25: =F14*IF(F5=1,Supuestos!$B$8,Supuestos!$B$7)/(1+Supuestos!$B$10) | G25: =G14*IF(G5=1,Supuestos!$B$8,Supuestos!$B$7)/(1+Supuestos!$B$10) | H25: =H14*IF(H5=1,Supuestos!$B$8,Supuestos!$B$7)/(1+Supuestos!$B$10) | I25: =I14*IF(I5=1,Supuestos!$B$8,Supuestos!$B$7)/(1+Supuestos!$B$10) | J25: =J14*IF(J5=1,Supuestos!$B$8,Supuestos!$B$7)/(1+Supuestos!$B$10) | ... Z25: =Z14*IF(Z5=1,Supuestos!$B$8,Supuestos!$B$7)/(1+Supuestos!$B$10)
A26: Plan Red | C26: =C16*Supuestos!$B$5/(1+Supuestos!$B$10) | D26: =D16*Supuestos!$B$5/(1+Supuestos!$B$10) | E26: =E16*Supuestos!$B$5/(1+Supuestos!$B$10) | F26: =F16*Supuestos!$B$5/(1+Supuestos!$B$10) | G26: =G16*Supuestos!$B$5/(1+Supuestos!$B$10) | H26: =H16*Supuestos!$B$5/(1+Supuestos!$B$10) | I26: =I16*Supuestos!$B$5/(1+Supuestos!$B$10) | J26: =J16*Supuestos!$B$5/(1+Supuestos!$B$10) | ... Z26: =Z16*Supuestos!$B$5/(1+Supuestos!$B$10)
A27: Plan Clínico | C27: =C17*Supuestos!$B$6/(1+Supuestos!$B$10) | D27: =D17*Supuestos!$B$6/(1+Supuestos!$B$10) | E27: =E17*Supuestos!$B$6/(1+Supuestos!$B$10) | F27: =F17*Supuestos!$B$6/(1+Supuestos!$B$10) | G27: =G17*Supuestos!$B$6/(1+Supuestos!$B$10) | H27: =H17*Supuestos!$B$6/(1+Supuestos!$B$10) | I27: =I17*Supuestos!$B$6/(1+Supuestos!$B$10) | J27: =J17*Supuestos!$B$6/(1+Supuestos!$B$10) | ... Z27: =Z17*Supuestos!$B$6/(1+Supuestos!$B$10)
A28: Canal Regene | C28: =C19*Supuestos!$B$6*(1-Supuestos!$B$58)/(1+Supuestos!$B$10) | D28: =D19*Supuestos!$B$6*(1-Supuestos!$B$58)/(1+Supuestos!$B$10) | E28: =E19*Supuestos!$B$6*(1-Supuestos!$B$58)/(1+Supuestos!$B$10) | F28: =F19*Supuestos!$B$6*(1-Supuestos!$B$58)/(1+Supuestos!$B$10) | G28: =G19*Supuestos!$B$6*(1-Supuestos!$B$58)/(1+Supuestos!$B$10) | H28: =H19*Supuestos!$B$6*(1-Supuestos!$B$58)/(1+Supuestos!$B$10) | I28: =I19*Supuestos!$B$6*(1-Supuestos!$B$58)/(1+Supuestos!$B$10) | J28: =J19*Supuestos!$B$6*(1-Supuestos!$B$58)/(1+Supuestos!$B$10) | ... Z28: =Z19*Supuestos!$B$6*(1-Supuestos!$B$58)/(1+Supuestos!$B$10)
A29: GB adicionales cobrados (médicos de alto consumo) | C29: =C21*Supuestos!$B$25*Supuestos!$B$26 | D29: =D21*Supuestos!$B$25*Supuestos!$B$26 | E29: =E21*Supuestos!$B$25*Supuestos!$B$26 | F29: =F21*Supuestos!$B$25*Supuestos!$B$26 | G29: =G21*Supuestos!$B$25*Supuestos!$B$26 | H29: =H21*Supuestos!$B$25*Supuestos!$B$26 | I29: =I21*Supuestos!$B$25*Supuestos!$B$26 | J29: =J21*Supuestos!$B$25*Supuestos!$B$26 | ... Z29: =Z21*Supuestos!$B$25*Supuestos!$B$26
A30: GB guardados en total (se conservan 5 años, NOM-004) | C30: =C21*Supuestos!$B$24+C29 | D30: =C30-C29+D21*Supuestos!$B$24+D29 | E30: =D30-D29+E21*Supuestos!$B$24+E29 | F30: =E30-E29+F21*Supuestos!$B$24+F29 | G30: =F30-F29+G21*Supuestos!$B$24+G29 | H30: =G30-G29+H21*Supuestos!$B$24+H29 | I30: =H30-H29+I21*Supuestos!$B$24+I29 | J30: =I30-I29+J21*Supuestos!$B$24+J29 | K30: =J30-J29+K21*Supuestos!$B$24+K29 | ... Z30: =Y30-Y29+Z21*Supuestos!$B$24+Z29
A31: Almacenamiento adicional | C31: =C29*Supuestos!$B$23/(1+Supuestos!$B$10) | D31: =D29*Supuestos!$B$23/(1+Supuestos!$B$10) | E31: =E29*Supuestos!$B$23/(1+Supuestos!$B$10) | F31: =F29*Supuestos!$B$23/(1+Supuestos!$B$10) | G31: =G29*Supuestos!$B$23/(1+Supuestos!$B$10) | H31: =H29*Supuestos!$B$23/(1+Supuestos!$B$10) | I31: =I29*Supuestos!$B$23/(1+Supuestos!$B$10) | J31: =J29*Supuestos!$B$23/(1+Supuestos!$B$10) | ... Z31: =Z29*Supuestos!$B$23/(1+Supuestos!$B$10)
A32: Ingreso recurrente mensual (MRR) | C32: =C25+C26+C27+C28+C31 | D32: =D25+D26+D27+D28+D31 | E32: =E25+E26+E27+E28+E31 | F32: =F25+F26+F27+F28+F31 | G32: =G25+G26+G27+G28+G31 | H32: =H25+H26+H27+H28+H31 | I32: =I25+I26+I27+I28+I31 | J32: =J25+J26+J27+J28+J31 | ... Z32: =Z25+Z26+Z27+Z28+Z31
A33: Migraciones vendidas | C33: =(C12+C15+C18)*Supuestos!$B$68 | D33: =(D12+D15+D18)*Supuestos!$B$68 | E33: =(E12+E15+E18)*Supuestos!$B$68 | F33: =(F12+F15+F18)*Supuestos!$B$68 | G33: =(G12+G15+G18)*Supuestos!$B$68 | H33: =(H12+H15+H18)*Supuestos!$B$68 | I33: =(I12+I15+I18)*Supuestos!$B$68 | J33: =(J12+J15+J18)*Supuestos!$B$68 | ... Z33: =(Z12+Z15+Z18)*Supuestos!$B$68
A34: Ingreso por migraciones | C34: =C33*Supuestos!$B$46*Supuestos!$B$11/(1+Supuestos!$B$10) | D34: =D33*Supuestos!$B$46*Supuestos!$B$11/(1+Supuestos!$B$10) | E34: =E33*Supuestos!$B$46*Supuestos!$B$11/(1+Supuestos!$B$10) | F34: =F33*Supuestos!$B$46*Supuestos!$B$11/(1+Supuestos!$B$10) | G34: =G33*Supuestos!$B$46*Supuestos!$B$11/(1+Supuestos!$B$10) | H34: =H33*Supuestos!$B$46*Supuestos!$B$11/(1+Supuestos!$B$10) | I34: =I33*Supuestos!$B$46*Supuestos!$B$11/(1+Supuestos!$B$10) | J34: =J33*Supuestos!$B$46*Supuestos!$B$11/(1+Supuestos!$B$10) | ... Z34: =Z33*Supuestos!$B$46*Supuestos!$B$11/(1+Supuestos!$B$10)
A35: INGRESO TOTAL | C35: =C32+C34 | D35: =D32+D34 | E35: =E32+E34 | F35: =F32+F34 | G35: =G32+G34 | H35: =H32+H34 | I35: =I32+I34 | J35: =J32+J34 | ... Z35: =Z32+Z34
A37: COSTOS VARIABLES
A38: IA (NOVA) | C38: =(C22*Supuestos!$B$17+C21*Supuestos!$B$18)*Supuestos!$B$14 | D38: =(D22*Supuestos!$B$17+D21*Supuestos!$B$18)*Supuestos!$B$14 | E38: =(E22*Supuestos!$B$17+E21*Supuestos!$B$18)*Supuestos!$B$14 | F38: =(F22*Supuestos!$B$17+F21*Supuestos!$B$18)*Supuestos!$B$14 | G38: =(G22*Supuestos!$B$17+G21*Supuestos!$B$18)*Supuestos!$B$14 | H38: =(H22*Supuestos!$B$17+H21*Supuestos!$B$18)*Supuestos!$B$14 | I38: =(I22*Supuestos!$B$17+I21*Supuestos!$B$18)*Supuestos!$B$14 | J38: =(J22*Supuestos!$B$17+J21*Supuestos!$B$18)*Supuestos!$B$14 | ... Z38: =(Z22*Supuestos!$B$17+Z21*Supuestos!$B$18)*Supuestos!$B$14
A39: Almacenamiento (2 copias) | C39: =C30*(Supuestos!$B$27+Supuestos!$B$28)*Supuestos!$B$14 | D39: =D30*(Supuestos!$B$27+Supuestos!$B$28)*Supuestos!$B$14 | E39: =E30*(Supuestos!$B$27+Supuestos!$B$28)*Supuestos!$B$14 | F39: =F30*(Supuestos!$B$27+Supuestos!$B$28)*Supuestos!$B$14 | G39: =G30*(Supuestos!$B$27+Supuestos!$B$28)*Supuestos!$B$14 | H39: =H30*(Supuestos!$B$27+Supuestos!$B$28)*Supuestos!$B$14 | I39: =I30*(Supuestos!$B$27+Supuestos!$B$28)*Supuestos!$B$14 | J39: =J30*(Supuestos!$B$27+Supuestos!$B$28)*Supuestos!$B$14 | ... Z39: =Z30*(Supuestos!$B$27+Supuestos!$B$28)*Supuestos!$B$14
A40: Comisión de cobro (con IVA de la comisión) | C40: =((C20+C33)*Supuestos!$B$32+C35*(1+Supuestos!$B$10)*Supuestos!$B$31)*(1+Supuestos!$B$10) | D40: =((D20+D33)*Supuestos!$B$32+D35*(1+Supuestos!$B$10)*Supuestos!$B$31)*(1+Supuestos!$B$10) | E40: =((E20+E33)*Supuestos!$B$32+E35*(1+Supuestos!$B$10)*Supuestos!$B$31)*(1+Supuestos!$B$10) | F40: =((F20+F33)*Supuestos!$B$32+F35*(1+Supuestos!$B$10)*Supuestos!$B$31)*(1+Supuestos!$B$10) | G40: =((G20+G33)*Supuestos!$B$32+G35*(1+Supuestos!$B$10)*Supuestos!$B$31)*(1+Supuestos!$B$10) | H40: =((H20+H33)*Supuestos!$B$32+H35*(1+Supuestos!$B$10)*Supuestos!$B$31)*(1+Supuestos!$B$10) | I40: =((I20+I33)*Supuestos!$B$32+I35*(1+Supuestos!$B$10)*Supuestos!$B$31)*(1+Supuestos!$B$10) | J40: =((J20+J33)*Supuestos!$B$32+J35*(1+Supuestos!$B$10)*Supuestos!$B$31)*(1+Supuestos!$B$10) | ... Z40: =((Z20+Z33)*Supuestos!$B$32+Z35*(1+Supuestos!$B$10)*Supuestos!$B$31)*(1+Supuestos!$B$10)
A41: Facturas CFDI | C41: =(C20+C33)*Supuestos!$B$33 | D41: =(D20+D33)*Supuestos!$B$33 | E41: =(E20+E33)*Supuestos!$B$33 | F41: =(F20+F33)*Supuestos!$B$33 | G41: =(G20+G33)*Supuestos!$B$33 | H41: =(H20+H33)*Supuestos!$B$33 | I41: =(I20+I33)*Supuestos!$B$33 | J41: =(J20+J33)*Supuestos!$B$33 | ... Z41: =(Z20+Z33)*Supuestos!$B$33
A42: Soporte | C42: =C20*Supuestos!$B$37*Supuestos!$B$38 | D42: =D20*Supuestos!$B$37*Supuestos!$B$38 | E42: =E20*Supuestos!$B$37*Supuestos!$B$38 | F42: =F20*Supuestos!$B$37*Supuestos!$B$38 | G42: =G20*Supuestos!$B$37*Supuestos!$B$38 | H42: =H20*Supuestos!$B$37*Supuestos!$B$38 | I42: =I20*Supuestos!$B$37*Supuestos!$B$38 | J42: =J20*Supuestos!$B$37*Supuestos!$B$38 | ... Z42: =Z20*Supuestos!$B$37*Supuestos!$B$38
A43: IA de las migraciones | C43: =C33*Supuestos!$B$46*Supuestos!$B$47*Supuestos!$B$48*Supuestos!$B$14 | D43: =D33*Supuestos!$B$46*Supuestos!$B$47*Supuestos!$B$48*Supuestos!$B$14 | E43: =E33*Supuestos!$B$46*Supuestos!$B$47*Supuestos!$B$48*Supuestos!$B$14 | F43: =F33*Supuestos!$B$46*Supuestos!$B$47*Supuestos!$B$48*Supuestos!$B$14 | G43: =G33*Supuestos!$B$46*Supuestos!$B$47*Supuestos!$B$48*Supuestos!$B$14 | H43: =H33*Supuestos!$B$46*Supuestos!$B$47*Supuestos!$B$48*Supuestos!$B$14 | I43: =I33*Supuestos!$B$46*Supuestos!$B$47*Supuestos!$B$48*Supuestos!$B$14 | J43: =J33*Supuestos!$B$46*Supuestos!$B$47*Supuestos!$B$48*Supuestos!$B$14 | ... Z43: =Z33*Supuestos!$B$46*Supuestos!$B$47*Supuestos!$B$48*Supuestos!$B$14
A44: Total costos variables | C44: =SUM(C38:C43) | D44: =SUM(D38:D43) | E44: =SUM(E38:E43) | F44: =SUM(F38:F43) | G44: =SUM(G38:G43) | H44: =SUM(H38:H43) | I44: =SUM(I38:I43) | J44: =SUM(J38:J43) | ... Z44: =SUM(Z38:Z43)
A45: MARGEN DE CONTRIBUCIÓN | C45: =C35-C44 | D45: =D35-D44 | E45: =E35-E44 | F45: =F35-F44 | G45: =G35-G44 | H45: =H35-H44 | I45: =I35-I44 | J45: =J35-J44 | ... Z45: =Z35-Z44
A46: Margen de contribución % | C46: =IF(C35=0,0,C45/C35) | D46: =IF(D35=0,0,D45/D35) | E46: =IF(E35=0,0,E45/E35) | F46: =IF(F35=0,0,F45/F35) | G46: =IF(G35=0,0,G45/G35) | H46: =IF(H35=0,0,H45/H35) | I46: =IF(I35=0,0,I45/I35) | J46: =IF(J35=0,0,J45/J35) | ... Z46: =IF(Z35=0,0,Z45/Z35)
A48: COSTOS FIJOS Y DE CRECIMIENTO
A49: Infraestructura | C49: =(Supuestos!$B$15+Supuestos!$B$16*C5+Supuestos!$B$61*INT(C20/100)+IF(C3>=Supuestos!$B$57-1,Supuestos!$B$59,0))*Supuestos!$B$14 | D49: =(Supuestos!$B$15+Supuestos!$B$16*D5+Supuestos!$B$61*INT(D20/100)+IF(D3>=Supuestos!$B$57-1,Supuestos!$B$59,0))*Supuestos!$B$14 | E49: =(Supuestos!$B$15+Supuestos!$B$16*E5+Supuestos!$B$61*INT(E20/100)+IF(E3>=Supuestos!$B$57-1,Supuestos!$B$59,0))*Supuestos!$B$14 | F49: =(Supuestos!$B$15+Supuestos!$B$16*F5+Supuestos!$B$61*INT(F20/100)+IF(F3>=Supuestos!$B$57-1,Supuestos!$B$59,0))*Supuestos!$B$14 | G49: =(Supuestos!$B$15+Supuestos!$B$16*G5+Supuestos!$B$61*INT(G20/100)+IF(G3>=Supuestos!$B$57-1,Supuestos!$B$59,0))*Supuestos!$B$14 | H49: =(Supuestos!$B$15+Supuestos!$B$16*H5+Supuestos!$B$61*INT(H20/100)+IF(H3>=Supuestos!$B$57-1,Supuestos!$B$59,0))*Supuestos!$B$14 | I49: =(Supuestos!$B$15+Supuestos!$B$16*I5+Supuestos!$B$61*INT(I20/100)+IF(I3>=Supuestos!$B$57-1,Supuestos!$B$59,0))*Supuestos!$B$14 | J49: =(Supuestos!$B$15+Supuestos!$B$16*J5+Supuestos!$B$61*INT(J20/100)+IF(J3>=Supuestos!$B$57-1,Supuestos!$B$59,0))*Supuestos!$B$14 | ... Z49: =(Supuestos!$B$15+Supuestos!$B$16*Z5+Supuestos!$B$61*INT(Z20/100)+IF(Z3>=Supuestos!$B$57-1,Supuestos!$B$59,0))*Supuestos!$B$14
A50: Contador | C50: =Supuestos!$B$36 | D50: =Supuestos!$B$36 | E50: =Supuestos!$B$36 | F50: =Supuestos!$B$36 | G50: =Supuestos!$B$36 | H50: =Supuestos!$B$36 | I50: =Supuestos!$B$36 | J50: =Supuestos!$B$36 | ... Z50: =Supuestos!$B$36
A51: Adquisición de médicos | C51: =C8*Supuestos!$B$39+C18*Supuestos!$B$60 | D51: =D8*Supuestos!$B$39+D18*Supuestos!$B$60 | E51: =E8*Supuestos!$B$39+E18*Supuestos!$B$60 | F51: =F8*Supuestos!$B$39+F18*Supuestos!$B$60 | G51: =G8*Supuestos!$B$39+G18*Supuestos!$B$60 | H51: =H8*Supuestos!$B$39+H18*Supuestos!$B$60 | I51: =I8*Supuestos!$B$39+I18*Supuestos!$B$60 | J51: =J8*Supuestos!$B$39+J18*Supuestos!$B$60 | ... Z51: =Z8*Supuestos!$B$39+Z18*Supuestos!$B$60
A52: Páginas a revisar (migración asistida) | C52: =C33*Supuestos!$B$46*Supuestos!$B$47 | D52: =D33*Supuestos!$B$46*Supuestos!$B$47 | E52: =E33*Supuestos!$B$46*Supuestos!$B$47 | F52: =F33*Supuestos!$B$46*Supuestos!$B$47 | G52: =G33*Supuestos!$B$46*Supuestos!$B$47 | H52: =H33*Supuestos!$B$46*Supuestos!$B$47 | I52: =I33*Supuestos!$B$46*Supuestos!$B$47 | J52: =J33*Supuestos!$B$46*Supuestos!$B$47 | ... Z52: =Z33*Supuestos!$B$46*Supuestos!$B$47
A53: Personas de migración | C53: =IF(C3>=Supuestos!$B$57-Supuestos!$B$52,MAX(1,ROUNDUP(C52*Supuestos!$B$49/60/Supuestos!$B$51,0)),ROUNDUP(C52*Supuestos!$B$49/60/Supuestos!$B$51,0)) | D53: =IF(D3>=Supuestos!$B$57-Supuestos!$B$52,MAX(1,ROUNDUP(D52*Supuestos!$B$49/60/Supuestos!$B$51,0)),ROUNDUP(D52*Supuestos!$B$49/60/Supuestos!$B$51,0)) | E53: =IF(E3>=Supuestos!$B$57-Supuestos!$B$52,MAX(1,ROUNDUP(E52*Supuestos!$B$49/60/Supuestos!$B$51,0)),ROUNDUP(E52*Supuestos!$B$49/60/Supuestos!$B$51,0)) | F53: =IF(F3>=Supuestos!$B$57-Supuestos!$B$52,MAX(1,ROUNDUP(F52*Supuestos!$B$49/60/Supuestos!$B$51,0)),ROUNDUP(F52*Supuestos!$B$49/60/Supuestos!$B$51,0)) | G53: =IF(G3>=Supuestos!$B$57-Supuestos!$B$52,MAX(1,ROUNDUP(G52*Supuestos!$B$49/60/Supuestos!$B$51,0)),ROUNDUP(G52*Supuestos!$B$49/60/Supuestos!$B$51,0)) | H53: =IF(H3>=Supuestos!$B$57-Supuestos!$B$52,MAX(1,ROUNDUP(H52*Supuestos!$B$49/60/Supuestos!$B$51,0)),ROUNDUP(H52*Supuestos!$B$49/60/Supuestos!$B$51,0)) | I53: =IF(I3>=Supuestos!$B$57-Supuestos!$B$52,MAX(1,ROUNDUP(I52*Supuestos!$B$49/60/Supuestos!$B$51,0)),ROUNDUP(I52*Supuestos!$B$49/60/Supuestos!$B$51,0)) | J53: =IF(J3>=Supuestos!$B$57-Supuestos!$B$52,MAX(1,ROUNDUP(J52*Supuestos!$B$49/60/Supuestos!$B$51,0)),ROUNDUP(J52*Supuestos!$B$49/60/Supuestos!$B$51,0)) | ... Z53: =IF(Z3>=Supuestos!$B$57-Supuestos!$B$52,MAX(1,ROUNDUP(Z52*Supuestos!$B$49/60/Supuestos!$B$51,0)),ROUNDUP(Z52*Supuestos!$B$49/60/Supuestos!$B$51,0))
A54: Personal de migración + capacitación | C54: =C53*Supuestos!$B$50+MAX(0,C53-0)*Supuestos!$B$53 | D54: =D53*Supuestos!$B$50+MAX(0,D53-C53)*Supuestos!$B$53 | E54: =E53*Supuestos!$B$50+MAX(0,E53-D53)*Supuestos!$B$53 | F54: =F53*Supuestos!$B$50+MAX(0,F53-E53)*Supuestos!$B$53 | G54: =G53*Supuestos!$B$50+MAX(0,G53-F53)*Supuestos!$B$53 | H54: =H53*Supuestos!$B$50+MAX(0,H53-G53)*Supuestos!$B$53 | I54: =I53*Supuestos!$B$50+MAX(0,I53-H53)*Supuestos!$B$53 | J54: =J53*Supuestos!$B$50+MAX(0,J53-I53)*Supuestos!$B$53 | K54: =K53*Supuestos!$B$50+MAX(0,K53-J53)*Supuestos!$B$53 | ... Z54: =Z53*Supuestos!$B$50+MAX(0,Z53-Y53)*Supuestos!$B$53
A55: Sueldo de Víctor | C55: =Supuestos!$B$40 | D55: =Supuestos!$B$40 | E55: =Supuestos!$B$40 | F55: =Supuestos!$B$40 | G55: =Supuestos!$B$40 | H55: =Supuestos!$B$40 | I55: =Supuestos!$B$40 | J55: =Supuestos!$B$40 | ... Z55: =Supuestos!$B$40
A56: Pagos únicos (abogado, prueba de penetración) | C56: =IF(C3=1,Supuestos!$B$41,0)+IF(C3=Supuestos!$B$43,Supuestos!$B$42,0) | D56: =IF(D3=1,Supuestos!$B$41,0)+IF(D3=Supuestos!$B$43,Supuestos!$B$42,0) | E56: =IF(E3=1,Supuestos!$B$41,0)+IF(E3=Supuestos!$B$43,Supuestos!$B$42,0) | F56: =IF(F3=1,Supuestos!$B$41,0)+IF(F3=Supuestos!$B$43,Supuestos!$B$42,0) | G56: =IF(G3=1,Supuestos!$B$41,0)+IF(G3=Supuestos!$B$43,Supuestos!$B$42,0) | H56: =IF(H3=1,Supuestos!$B$41,0)+IF(H3=Supuestos!$B$43,Supuestos!$B$42,0) | I56: =IF(I3=1,Supuestos!$B$41,0)+IF(I3=Supuestos!$B$43,Supuestos!$B$42,0) | J56: =IF(J3=1,Supuestos!$B$41,0)+IF(J3=Supuestos!$B$43,Supuestos!$B$42,0) | ... Z56: =IF(Z3=1,Supuestos!$B$41,0)+IF(Z3=Supuestos!$B$43,Supuestos!$B$42,0)
A57: Total fijos y crecimiento | C57: =C49+C50+C51+C54+C55+C56 | D57: =D49+D50+D51+D54+D55+D56 | E57: =E49+E50+E51+E54+E55+E56 | F57: =F49+F50+F51+F54+F55+F56 | G57: =G49+G50+G51+G54+G55+G56 | H57: =H49+H50+H51+H54+H55+H56 | I57: =I49+I50+I51+I54+I55+I56 | J57: =J49+J50+J51+J54+J55+J56 | ... Z57: =Z49+Z50+Z51+Z54+Z55+Z56
A59: FLUJO NETO DEL MES | C59: =C45-C57 | D59: =D45-D57 | E59: =E45-E57 | F59: =F45-F57 | G59: =G45-G57 | H59: =H45-H57 | I59: =I45-I57 | J59: =J45-J57 | ... Z59: =Z45-Z57
A60: FLUJO ACUMULADO | C60: =C59 | D60: =C60+D59 | E60: =D60+E59 | F60: =E60+F59 | G60: =F60+G59 | H60: =G60+H59 | I60: =H60+I59 | J60: =I60+J59 | K60: =J60+K59 | ... Z60: =Y60+Z59
A61: Ingreso recurrente anualizado (ARR) | C61: =C32*12 | D61: =D32*12 | E61: =E32*12 | F61: =F32*12 | G61: =G32*12 | H61: =H32*12 | I61: =I32*12 | J61: =J32*12 | ... Z61: =Z32*12
A62: Ayuda: mes con flujo positivo (99 = no) | C62: =IF(C59>0,C3,99) | D62: =IF(D59>0,D3,99) | E62: =IF(E59>0,E3,99) | F62: =IF(F59>0,F3,99) | G62: =IF(G59>0,G3,99) | H62: =IF(H59>0,H3,99) | I62: =IF(I59>0,I3,99) | J62: =IF(J59>0,J3,99) | ... Z62: =IF(Z59>0,Z3,99)

Sheet Base
A1: Escenario Base — mes a mes (MXN sin IVA)
A3: Mes # | C3: 1 | D3: 2 | E3: 3 | F3: 4 | G3: 5 | H3: 6 | I3: 7 | J3: 8 | K3: 9 | L3: 10 | M3: 11 | N3: 12 | O3: 13 | P3: 14 | Q3: 15 | R3: 16 | S3: 17 | T3: 18 | U3: 19 | V3: 20 | W3: 21 | X3: 22 | Y3: 23 | Z3: 24
A4: Mes | C4: dic-2026 | D4: ene-2027 | E4: feb-2027 | F4: mar-2027 | G4: abr-2027 | H4: may-2027 | I4: jun-2027 | J4: jul-2027 | K4: ago-2027 | L4: sep-2027 | M4: oct-2027 | N4: nov-2027 | O4: dic-2027 | P4: ene-2028 | Q4: feb-2028 | R4: mar-2028 | S4: abr-2028 | T4: may-2028 | U4: jun-2028 | V4: jul-2028 | W4: ago-2028 | X4: sep-2028 | Y4: oct-2028 | Z4: nov-2028
A5: Plan Clínico disponible (1 = sí) | C5: =IF(C3>=Supuestos!$B$43,1,0) | D5: =IF(D3>=Supuestos!$B$43,1,0) | E5: =IF(E3>=Supuestos!$B$43,1,0) | F5: =IF(F3>=Supuestos!$B$43,1,0) | G5: =IF(G3>=Supuestos!$B$43,1,0) | H5: =IF(H3>=Supuestos!$B$43,1,0) | I5: =IF(I3>=Supuestos!$B$43,1,0) | J5: =IF(J3>=Supuestos!$B$43,1,0) | ... Z5: =IF(Z3>=Supuestos!$B$43,1,0)
A7: MÉDICOS
A8: Médicos nuevos | C8: =Supuestos!$C$64 | D8: =Supuestos!$C$64 | E8: =Supuestos!$C$64 | F8: =Supuestos!$C$64 | G8: =Supuestos!$C$64 | H8: =Supuestos!$C$64 | I8: =Supuestos!$C$64 | J8: =Supuestos!$C$64 | ... Z8: =Supuestos!$C$64
A9: Fundadores nuevos | C9: =MIN(C8,Supuestos!$B$9) | D9: =MIN(D8,Supuestos!$B$9-C10) | E9: =MIN(E8,Supuestos!$B$9-D10) | F9: =MIN(F8,Supuestos!$B$9-E10) | G9: =MIN(G8,Supuestos!$B$9-F10) | H9: =MIN(H8,Supuestos!$B$9-G10) | I9: =MIN(I8,Supuestos!$B$9-H10) | J9: =MIN(J8,Supuestos!$B$9-I10) | K9: =MIN(K8,Supuestos!$B$9-J10) | ... Z9: =MIN(Z8,Supuestos!$B$9-Y10)
A10: Fundadores inscritos (acumulado) | C10: =C9 | D10: =C10+D9 | E10: =D10+E9 | F10: =E10+F9 | G10: =F10+G9 | H10: =G10+H9 | I10: =H10+I9 | J10: =I10+J9 | K10: =J10+K9 | ... Z10: =Y10+Z9
A11: Nuevos no fundadores | C11: =C8-C9 | D11: =D8-D9 | E11: =E8-E9 | F11: =F8-F9 | G11: =G8-G9 | H11: =H8-H9 | I11: =I8-I9 | J11: =J8-J9 | ... Z11: =Z8-Z9
A12: Nuevos que eligen Clínico | C12: =C11*C5*Supuestos!$C$66 | D12: =D11*D5*Supuestos!$C$66 | E12: =E11*E5*Supuestos!$C$66 | F12: =F11*F5*Supuestos!$C$66 | G12: =G11*G5*Supuestos!$C$66 | H12: =H11*H5*Supuestos!$C$66 | I12: =I11*I5*Supuestos!$C$66 | J12: =J11*J5*Supuestos!$C$66 | ... Z12: =Z11*Z5*Supuestos!$C$66
A13: Nuevos que eligen Red | C13: =C11-C12 | D13: =D11-D12 | E13: =E11-E12 | F13: =F11-F12 | G13: =G11-G12 | H13: =H11-H12 | I13: =I11-I12 | J13: =J11-J12 | ... Z13: =Z11-Z12
A14: Fundadores activos | C14: =C9 | D14: =C14*(1-Supuestos!$C$65)+D9 | E14: =D14*(1-Supuestos!$C$65)+E9 | F14: =E14*(1-Supuestos!$C$65)+F9 | G14: =F14*(1-Supuestos!$C$65)+G9 | H14: =G14*(1-Supuestos!$C$65)+H9 | I14: =H14*(1-Supuestos!$C$65)+I9 | J14: =I14*(1-Supuestos!$C$65)+J9 | K14: =J14*(1-Supuestos!$C$65)+K9 | ... Z14: =Y14*(1-Supuestos!$C$65)+Z9
A15: Suben de Red a Clínico | C15: =0 | D15: =C16*(1-Supuestos!$C$65)*D5*Supuestos!$C$67 | E15: =D16*(1-Supuestos!$C$65)*E5*Supuestos!$C$67 | F15: =E16*(1-Supuestos!$C$65)*F5*Supuestos!$C$67 | G15: =F16*(1-Supuestos!$C$65)*G5*Supuestos!$C$67 | H15: =G16*(1-Supuestos!$C$65)*H5*Supuestos!$C$67 | I15: =H16*(1-Supuestos!$C$65)*I5*Supuestos!$C$67 | J15: =I16*(1-Supuestos!$C$65)*J5*Supuestos!$C$67 | K15: =J16*(1-Supuestos!$C$65)*K5*Supuestos!$C$67 | ... Z15: =Y16*(1-Supuestos!$C$65)*Z5*Supuestos!$C$67
A16: Red activos | C16: =C13 | D16: =C16*(1-Supuestos!$C$65)-D15+D13 | E16: =D16*(1-Supuestos!$C$65)-E15+E13 | F16: =E16*(1-Supuestos!$C$65)-F15+F13 | G16: =F16*(1-Supuestos!$C$65)-G15+G13 | H16: =G16*(1-Supuestos!$C$65)-H15+H13 | I16: =H16*(1-Supuestos!$C$65)-I15+I13 | J16: =I16*(1-Supuestos!$C$65)-J15+J13 | K16: =J16*(1-Supuestos!$C$65)-K15+K13 | ... Z16: =Y16*(1-Supuestos!$C$65)-Z15+Z13
A17: Clínico activos (precio completo) | C17: =C12 | D17: =C17*(1-Supuestos!$C$65)+D12+D15 | E17: =D17*(1-Supuestos!$C$65)+E12+E15 | F17: =E17*(1-Supuestos!$C$65)+F12+F15 | G17: =F17*(1-Supuestos!$C$65)+G12+G15 | H17: =G17*(1-Supuestos!$C$65)+H12+H15 | I17: =H17*(1-Supuestos!$C$65)+I12+I15 | J17: =I17*(1-Supuestos!$C$65)+J12+J15 | K17: =J17*(1-Supuestos!$C$65)+K12+K15 | ... Z17: =Y17*(1-Supuestos!$C$65)+Z12+Z15
A18: Médicos Regene nuevos | C18: =IF(C3>=Supuestos!$B$57,Supuestos!$B$56*Supuestos!$C$69/MAX(1,25-Supuestos!$B$57),0) | D18: =IF(D3>=Supuestos!$B$57,Supuestos!$B$56*Supuestos!$C$69/MAX(1,25-Supuestos!$B$57),0) | E18: =IF(E3>=Supuestos!$B$57,Supuestos!$B$56*Supuestos!$C$69/MAX(1,25-Supuestos!$B$57),0) | F18: =IF(F3>=Supuestos!$B$57,Supuestos!$B$56*Supuestos!$C$69/MAX(1,25-Supuestos!$B$57),0) | G18: =IF(G3>=Supuestos!$B$57,Supuestos!$B$56*Supuestos!$C$69/MAX(1,25-Supuestos!$B$57),0) | H18: =IF(H3>=Supuestos!$B$57,Supuestos!$B$56*Supuestos!$C$69/MAX(1,25-Supuestos!$B$57),0) | I18: =IF(I3>=Supuestos!$B$57,Supuestos!$B$56*Supuestos!$C$69/MAX(1,25-Supuestos!$B$57),0) | J18: =IF(J3>=Supuestos!$B$57,Supuestos!$B$56*Supuestos!$C$69/MAX(1,25-Supuestos!$B$57),0) | ... Z18: =IF(Z3>=Supuestos!$B$57,Supuestos!$B$56*Supuestos!$C$69/MAX(1,25-Supuestos!$B$57),0)
A19: Médicos Regene activos (Clínico con descuento) | C19: =C18 | D19: =C19*(1-Supuestos!$C$65)+D18 | E19: =D19*(1-Supuestos!$C$65)+E18 | F19: =E19*(1-Supuestos!$C$65)+F18 | G19: =F19*(1-Supuestos!$C$65)+G18 | H19: =G19*(1-Supuestos!$C$65)+H18 | I19: =H19*(1-Supuestos!$C$65)+I18 | J19: =I19*(1-Supuestos!$C$65)+J18 | K19: =J19*(1-Supuestos!$C$65)+K18 | ... Z19: =Y19*(1-Supuestos!$C$65)+Z18
A20: Total médicos activos | C20: =C14+C16+C17+C19 | D20: =D14+D16+D17+D19 | E20: =E14+E16+E17+E19 | F20: =F14+F16+F17+F19 | G20: =G14+G16+G17+G19 | H20: =H14+H16+H17+H19 | I20: =I14+I16+I17+I19 | J20: =J14+J16+J17+J19 | ... Z20: =Z14+Z16+Z17+Z19
A21: Médicos usando el portal clínico | C21: =C17+C19+C14*C5 | D21: =D17+D19+D14*D5 | E21: =E17+E19+E14*E5 | F21: =F17+F19+F14*F5 | G21: =G17+G19+G14*G5 | H21: =H17+H19+H14*H5 | I21: =I17+I19+I14*I5 | J21: =J17+J19+J14*J5 | ... Z21: =Z17+Z19+Z14*Z5
A22: Médicos usando solo Red | C22: =C20-C21 | D22: =D20-D21 | E22: =E20-E21 | F22: =F20-F21 | G22: =G20-G21 | H22: =H20-H21 | I22: =I20-I21 | J22: =J20-J21 | ... Z22: =Z20-Z21
A24: INGRESOS
A25: Fundadores | C25: =C14*IF(C5=1,Supuestos!$B$8,Supuestos!$B$7)/(1+Supuestos!$B$10) | D25: =D14*IF(D5=1,Supuestos!$B$8,Supuestos!$B$7)/(1+Supuestos!$B$10) | E25: =E14*IF(E5=1,Supuestos!$B$8,Supuestos!$B$7)/(1+Supuestos!$B$10) | F25: =F14*IF(F5=1,Supuestos!$B$8,Supuestos!$B$7)/(1+Supuestos!$B$10) | G25: =G14*IF(G5=1,Supuestos!$B$8,Supuestos!$B$7)/(1+Supuestos!$B$10) | H25: =H14*IF(H5=1,Supuestos!$B$8,Supuestos!$B$7)/(1+Supuestos!$B$10) | I25: =I14*IF(I5=1,Supuestos!$B$8,Supuestos!$B$7)/(1+Supuestos!$B$10) | J25: =J14*IF(J5=1,Supuestos!$B$8,Supuestos!$B$7)/(1+Supuestos!$B$10) | ... Z25: =Z14*IF(Z5=1,Supuestos!$B$8,Supuestos!$B$7)/(1+Supuestos!$B$10)
A26: Plan Red | C26: =C16*Supuestos!$B$5/(1+Supuestos!$B$10) | D26: =D16*Supuestos!$B$5/(1+Supuestos!$B$10) | E26: =E16*Supuestos!$B$5/(1+Supuestos!$B$10) | F26: =F16*Supuestos!$B$5/(1+Supuestos!$B$10) | G26: =G16*Supuestos!$B$5/(1+Supuestos!$B$10) | H26: =H16*Supuestos!$B$5/(1+Supuestos!$B$10) | I26: =I16*Supuestos!$B$5/(1+Supuestos!$B$10) | J26: =J16*Supuestos!$B$5/(1+Supuestos!$B$10) | ... Z26: =Z16*Supuestos!$B$5/(1+Supuestos!$B$10)
A27: Plan Clínico | C27: =C17*Supuestos!$B$6/(1+Supuestos!$B$10) | D27: =D17*Supuestos!$B$6/(1+Supuestos!$B$10) | E27: =E17*Supuestos!$B$6/(1+Supuestos!$B$10) | F27: =F17*Supuestos!$B$6/(1+Supuestos!$B$10) | G27: =G17*Supuestos!$B$6/(1+Supuestos!$B$10) | H27: =H17*Supuestos!$B$6/(1+Supuestos!$B$10) | I27: =I17*Supuestos!$B$6/(1+Supuestos!$B$10) | J27: =J17*Supuestos!$B$6/(1+Supuestos!$B$10) | ... Z27: =Z17*Supuestos!$B$6/(1+Supuestos!$B$10)
A28: Canal Regene | C28: =C19*Supuestos!$B$6*(1-Supuestos!$B$58)/(1+Supuestos!$B$10) | D28: =D19*Supuestos!$B$6*(1-Supuestos!$B$58)/(1+Supuestos!$B$10) | E28: =E19*Supuestos!$B$6*(1-Supuestos!$B$58)/(1+Supuestos!$B$10) | F28: =F19*Supuestos!$B$6*(1-Supuestos!$B$58)/(1+Supuestos!$B$10) | G28: =G19*Supuestos!$B$6*(1-Supuestos!$B$58)/(1+Supuestos!$B$10) | H28: =H19*Supuestos!$B$6*(1-Supuestos!$B$58)/(1+Supuestos!$B$10) | I28: =I19*Supuestos!$B$6*(1-Supuestos!$B$58)/(1+Supuestos!$B$10) | J28: =J19*Supuestos!$B$6*(1-Supuestos!$B$58)/(1+Supuestos!$B$10) | ... Z28: =Z19*Supuestos!$B$6*(1-Supuestos!$B$58)/(1+Supuestos!$B$10)
A29: GB adicionales cobrados (médicos de alto consumo) | C29: =C21*Supuestos!$B$25*Supuestos!$B$26 | D29: =D21*Supuestos!$B$25*Supuestos!$B$26 | E29: =E21*Supuestos!$B$25*Supuestos!$B$26 | F29: =F21*Supuestos!$B$25*Supuestos!$B$26 | G29: =G21*Supuestos!$B$25*Supuestos!$B$26 | H29: =H21*Supuestos!$B$25*Supuestos!$B$26 | I29: =I21*Supuestos!$B$25*Supuestos!$B$26 | J29: =J21*Supuestos!$B$25*Supuestos!$B$26 | ... Z29: =Z21*Supuestos!$B$25*Supuestos!$B$26
A30: GB guardados en total (se conservan 5 años, NOM-004) | C30: =C21*Supuestos!$B$24+C29 | D30: =C30-C29+D21*Supuestos!$B$24+D29 | E30: =D30-D29+E21*Supuestos!$B$24+E29 | F30: =E30-E29+F21*Supuestos!$B$24+F29 | G30: =F30-F29+G21*Supuestos!$B$24+G29 | H30: =G30-G29+H21*Supuestos!$B$24+H29 | I30: =H30-H29+I21*Supuestos!$B$24+I29 | J30: =I30-I29+J21*Supuestos!$B$24+J29 | K30: =J30-J29+K21*Supuestos!$B$24+K29 | ... Z30: =Y30-Y29+Z21*Supuestos!$B$24+Z29
A31: Almacenamiento adicional | C31: =C29*Supuestos!$B$23/(1+Supuestos!$B$10) | D31: =D29*Supuestos!$B$23/(1+Supuestos!$B$10) | E31: =E29*Supuestos!$B$23/(1+Supuestos!$B$10) | F31: =F29*Supuestos!$B$23/(1+Supuestos!$B$10) | G31: =G29*Supuestos!$B$23/(1+Supuestos!$B$10) | H31: =H29*Supuestos!$B$23/(1+Supuestos!$B$10) | I31: =I29*Supuestos!$B$23/(1+Supuestos!$B$10) | J31: =J29*Supuestos!$B$23/(1+Supuestos!$B$10) | ... Z31: =Z29*Supuestos!$B$23/(1+Supuestos!$B$10)
A32: Ingreso recurrente mensual (MRR) | C32: =C25+C26+C27+C28+C31 | D32: =D25+D26+D27+D28+D31 | E32: =E25+E26+E27+E28+E31 | F32: =F25+F26+F27+F28+F31 | G32: =G25+G26+G27+G28+G31 | H32: =H25+H26+H27+H28+H31 | I32: =I25+I26+I27+I28+I31 | J32: =J25+J26+J27+J28+J31 | ... Z32: =Z25+Z26+Z27+Z28+Z31
A33: Migraciones vendidas | C33: =(C12+C15+C18)*Supuestos!$C$68 | D33: =(D12+D15+D18)*Supuestos!$C$68 | E33: =(E12+E15+E18)*Supuestos!$C$68 | F33: =(F12+F15+F18)*Supuestos!$C$68 | G33: =(G12+G15+G18)*Supuestos!$C$68 | H33: =(H12+H15+H18)*Supuestos!$C$68 | I33: =(I12+I15+I18)*Supuestos!$C$68 | J33: =(J12+J15+J18)*Supuestos!$C$68 | ... Z33: =(Z12+Z15+Z18)*Supuestos!$C$68
A34: Ingreso por migraciones | C34: =C33*Supuestos!$B$46*Supuestos!$B$11/(1+Supuestos!$B$10) | D34: =D33*Supuestos!$B$46*Supuestos!$B$11/(1+Supuestos!$B$10) | E34: =E33*Supuestos!$B$46*Supuestos!$B$11/(1+Supuestos!$B$10) | F34: =F33*Supuestos!$B$46*Supuestos!$B$11/(1+Supuestos!$B$10) | G34: =G33*Supuestos!$B$46*Supuestos!$B$11/(1+Supuestos!$B$10) | H34: =H33*Supuestos!$B$46*Supuestos!$B$11/(1+Supuestos!$B$10) | I34: =I33*Supuestos!$B$46*Supuestos!$B$11/(1+Supuestos!$B$10) | J34: =J33*Supuestos!$B$46*Supuestos!$B$11/(1+Supuestos!$B$10) | ... Z34: =Z33*Supuestos!$B$46*Supuestos!$B$11/(1+Supuestos!$B$10)
A35: INGRESO TOTAL | C35: =C32+C34 | D35: =D32+D34 | E35: =E32+E34 | F35: =F32+F34 | G35: =G32+G34 | H35: =H32+H34 | I35: =I32+I34 | J35: =J32+J34 | ... Z35: =Z32+Z34
A37: COSTOS VARIABLES
A38: IA (NOVA) | C38: =(C22*Supuestos!$B$17+C21*Supuestos!$B$18)*Supuestos!$B$14 | D38: =(D22*Supuestos!$B$17+D21*Supuestos!$B$18)*Supuestos!$B$14 | E38: =(E22*Supuestos!$B$17+E21*Supuestos!$B$18)*Supuestos!$B$14 | F38: =(F22*Supuestos!$B$17+F21*Supuestos!$B$18)*Supuestos!$B$14 | G38: =(G22*Supuestos!$B$17+G21*Supuestos!$B$18)*Supuestos!$B$14 | H38: =(H22*Supuestos!$B$17+H21*Supuestos!$B$18)*Supuestos!$B$14 | I38: =(I22*Supuestos!$B$17+I21*Supuestos!$B$18)*Supuestos!$B$14 | J38: =(J22*Supuestos!$B$17+J21*Supuestos!$B$18)*Supuestos!$B$14 | ... Z38: =(Z22*Supuestos!$B$17+Z21*Supuestos!$B$18)*Supuestos!$B$14
A39: Almacenamiento (2 copias) | C39: =C30*(Supuestos!$B$27+Supuestos!$B$28)*Supuestos!$B$14 | D39: =D30*(Supuestos!$B$27+Supuestos!$B$28)*Supuestos!$B$14 | E39: =E30*(Supuestos!$B$27+Supuestos!$B$28)*Supuestos!$B$14 | F39: =F30*(Supuestos!$B$27+Supuestos!$B$28)*Supuestos!$B$14 | G39: =G30*(Supuestos!$B$27+Supuestos!$B$28)*Supuestos!$B$14 | H39: =H30*(Supuestos!$B$27+Supuestos!$B$28)*Supuestos!$B$14 | I39: =I30*(Supuestos!$B$27+Supuestos!$B$28)*Supuestos!$B$14 | J39: =J30*(Supuestos!$B$27+Supuestos!$B$28)*Supuestos!$B$14 | ... Z39: =Z30*(Supuestos!$B$27+Supuestos!$B$28)*Supuestos!$B$14
A40: Comisión de cobro (con IVA de la comisión) | C40: =((C20+C33)*Supuestos!$B$32+C35*(1+Supuestos!$B$10)*Supuestos!$B$31)*(1+Supuestos!$B$10) | D40: =((D20+D33)*Supuestos!$B$32+D35*(1+Supuestos!$B$10)*Supuestos!$B$31)*(1+Supuestos!$B$10) | E40: =((E20+E33)*Supuestos!$B$32+E35*(1+Supuestos!$B$10)*Supuestos!$B$31)*(1+Supuestos!$B$10) | F40: =((F20+F33)*Supuestos!$B$32+F35*(1+Supuestos!$B$10)*Supuestos!$B$31)*(1+Supuestos!$B$10) | G40: =((G20+G33)*Supuestos!$B$32+G35*(1+Supuestos!$B$10)*Supuestos!$B$31)*(1+Supuestos!$B$10) | H40: =((H20+H33)*Supuestos!$B$32+H35*(1+Supuestos!$B$10)*Supuestos!$B$31)*(1+Supuestos!$B$10) | I40: =((I20+I33)*Supuestos!$B$32+I35*(1+Supuestos!$B$10)*Supuestos!$B$31)*(1+Supuestos!$B$10) | J40: =((J20+J33)*Supuestos!$B$32+J35*(1+Supuestos!$B$10)*Supuestos!$B$31)*(1+Supuestos!$B$10) | ... Z40: =((Z20+Z33)*Supuestos!$B$32+Z35*(1+Supuestos!$B$10)*Supuestos!$B$31)*(1+Supuestos!$B$10)
A41: Facturas CFDI | C41: =(C20+C33)*Supuestos!$B$33 | D41: =(D20+D33)*Supuestos!$B$33 | E41: =(E20+E33)*Supuestos!$B$33 | F41: =(F20+F33)*Supuestos!$B$33 | G41: =(G20+G33)*Supuestos!$B$33 | H41: =(H20+H33)*Supuestos!$B$33 | I41: =(I20+I33)*Supuestos!$B$33 | J41: =(J20+J33)*Supuestos!$B$33 | ... Z41: =(Z20+Z33)*Supuestos!$B$33
A42: Soporte | C42: =C20*Supuestos!$B$37*Supuestos!$B$38 | D42: =D20*Supuestos!$B$37*Supuestos!$B$38 | E42: =E20*Supuestos!$B$37*Supuestos!$B$38 | F42: =F20*Supuestos!$B$37*Supuestos!$B$38 | G42: =G20*Supuestos!$B$37*Supuestos!$B$38 | H42: =H20*Supuestos!$B$37*Supuestos!$B$38 | I42: =I20*Supuestos!$B$37*Supuestos!$B$38 | J42: =J20*Supuestos!$B$37*Supuestos!$B$38 | ... Z42: =Z20*Supuestos!$B$37*Supuestos!$B$38
A43: IA de las migraciones | C43: =C33*Supuestos!$B$46*Supuestos!$B$47*Supuestos!$B$48*Supuestos!$B$14 | D43: =D33*Supuestos!$B$46*Supuestos!$B$47*Supuestos!$B$48*Supuestos!$B$14 | E43: =E33*Supuestos!$B$46*Supuestos!$B$47*Supuestos!$B$48*Supuestos!$B$14 | F43: =F33*Supuestos!$B$46*Supuestos!$B$47*Supuestos!$B$48*Supuestos!$B$14 | G43: =G33*Supuestos!$B$46*Supuestos!$B$47*Supuestos!$B$48*Supuestos!$B$14 | H43: =H33*Supuestos!$B$46*Supuestos!$B$47*Supuestos!$B$48*Supuestos!$B$14 | I43: =I33*Supuestos!$B$46*Supuestos!$B$47*Supuestos!$B$48*Supuestos!$B$14 | J43: =J33*Supuestos!$B$46*Supuestos!$B$47*Supuestos!$B$48*Supuestos!$B$14 | ... Z43: =Z33*Supuestos!$B$46*Supuestos!$B$47*Supuestos!$B$48*Supuestos!$B$14
A44: Total costos variables | C44: =SUM(C38:C43) | D44: =SUM(D38:D43) | E44: =SUM(E38:E43) | F44: =SUM(F38:F43) | G44: =SUM(G38:G43) | H44: =SUM(H38:H43) | I44: =SUM(I38:I43) | J44: =SUM(J38:J43) | ... Z44: =SUM(Z38:Z43)
A45: MARGEN DE CONTRIBUCIÓN | C45: =C35-C44 | D45: =D35-D44 | E45: =E35-E44 | F45: =F35-F44 | G45: =G35-G44 | H45: =H35-H44 | I45: =I35-I44 | J45: =J35-J44 | ... Z45: =Z35-Z44
A46: Margen de contribución % | C46: =IF(C35=0,0,C45/C35) | D46: =IF(D35=0,0,D45/D35) | E46: =IF(E35=0,0,E45/E35) | F46: =IF(F35=0,0,F45/F35) | G46: =IF(G35=0,0,G45/G35) | H46: =IF(H35=0,0,H45/H35) | I46: =IF(I35=0,0,I45/I35) | J46: =IF(J35=0,0,J45/J35) | ... Z46: =IF(Z35=0,0,Z45/Z35)
A48: COSTOS FIJOS Y DE CRECIMIENTO
A49: Infraestructura | C49: =(Supuestos!$B$15+Supuestos!$B$16*C5+Supuestos!$B$61*INT(C20/100)+IF(C3>=Supuestos!$B$57-1,Supuestos!$B$59,0))*Supuestos!$B$14 | D49: =(Supuestos!$B$15+Supuestos!$B$16*D5+Supuestos!$B$61*INT(D20/100)+IF(D3>=Supuestos!$B$57-1,Supuestos!$B$59,0))*Supuestos!$B$14 | E49: =(Supuestos!$B$15+Supuestos!$B$16*E5+Supuestos!$B$61*INT(E20/100)+IF(E3>=Supuestos!$B$57-1,Supuestos!$B$59,0))*Supuestos!$B$14 | F49: =(Supuestos!$B$15+Supuestos!$B$16*F5+Supuestos!$B$61*INT(F20/100)+IF(F3>=Supuestos!$B$57-1,Supuestos!$B$59,0))*Supuestos!$B$14 | G49: =(Supuestos!$B$15+Supuestos!$B$16*G5+Supuestos!$B$61*INT(G20/100)+IF(G3>=Supuestos!$B$57-1,Supuestos!$B$59,0))*Supuestos!$B$14 | H49: =(Supuestos!$B$15+Supuestos!$B$16*H5+Supuestos!$B$61*INT(H20/100)+IF(H3>=Supuestos!$B$57-1,Supuestos!$B$59,0))*Supuestos!$B$14 | I49: =(Supuestos!$B$15+Supuestos!$B$16*I5+Supuestos!$B$61*INT(I20/100)+IF(I3>=Supuestos!$B$57-1,Supuestos!$B$59,0))*Supuestos!$B$14 | J49: =(Supuestos!$B$15+Supuestos!$B$16*J5+Supuestos!$B$61*INT(J20/100)+IF(J3>=Supuestos!$B$57-1,Supuestos!$B$59,0))*Supuestos!$B$14 | ... Z49: =(Supuestos!$B$15+Supuestos!$B$16*Z5+Supuestos!$B$61*INT(Z20/100)+IF(Z3>=Supuestos!$B$57-1,Supuestos!$B$59,0))*Supuestos!$B$14
A50: Contador | C50: =Supuestos!$B$36 | D50: =Supuestos!$B$36 | E50: =Supuestos!$B$36 | F50: =Supuestos!$B$36 | G50: =Supuestos!$B$36 | H50: =Supuestos!$B$36 | I50: =Supuestos!$B$36 | J50: =Supuestos!$B$36 | ... Z50: =Supuestos!$B$36
A51: Adquisición de médicos | C51: =C8*Supuestos!$B$39+C18*Supuestos!$B$60 | D51: =D8*Supuestos!$B$39+D18*Supuestos!$B$60 | E51: =E8*Supuestos!$B$39+E18*Supuestos!$B$60 | F51: =F8*Supuestos!$B$39+F18*Supuestos!$B$60 | G51: =G8*Supuestos!$B$39+G18*Supuestos!$B$60 | H51: =H8*Supuestos!$B$39+H18*Supuestos!$B$60 | I51: =I8*Supuestos!$B$39+I18*Supuestos!$B$60 | J51: =J8*Supuestos!$B$39+J18*Supuestos!$B$60 | ... Z51: =Z8*Supuestos!$B$39+Z18*Supuestos!$B$60
A52: Páginas a revisar (migración asistida) | C52: =C33*Supuestos!$B$46*Supuestos!$B$47 | D52: =D33*Supuestos!$B$46*Supuestos!$B$47 | E52: =E33*Supuestos!$B$46*Supuestos!$B$47 | F52: =F33*Supuestos!$B$46*Supuestos!$B$47 | G52: =G33*Supuestos!$B$46*Supuestos!$B$47 | H52: =H33*Supuestos!$B$46*Supuestos!$B$47 | I52: =I33*Supuestos!$B$46*Supuestos!$B$47 | J52: =J33*Supuestos!$B$46*Supuestos!$B$47 | ... Z52: =Z33*Supuestos!$B$46*Supuestos!$B$47
A53: Personas de migración | C53: =IF(C3>=Supuestos!$B$57-Supuestos!$B$52,MAX(1,ROUNDUP(C52*Supuestos!$B$49/60/Supuestos!$B$51,0)),ROUNDUP(C52*Supuestos!$B$49/60/Supuestos!$B$51,0)) | D53: =IF(D3>=Supuestos!$B$57-Supuestos!$B$52,MAX(1,ROUNDUP(D52*Supuestos!$B$49/60/Supuestos!$B$51,0)),ROUNDUP(D52*Supuestos!$B$49/60/Supuestos!$B$51,0)) | E53: =IF(E3>=Supuestos!$B$57-Supuestos!$B$52,MAX(1,ROUNDUP(E52*Supuestos!$B$49/60/Supuestos!$B$51,0)),ROUNDUP(E52*Supuestos!$B$49/60/Supuestos!$B$51,0)) | F53: =IF(F3>=Supuestos!$B$57-Supuestos!$B$52,MAX(1,ROUNDUP(F52*Supuestos!$B$49/60/Supuestos!$B$51,0)),ROUNDUP(F52*Supuestos!$B$49/60/Supuestos!$B$51,0)) | G53: =IF(G3>=Supuestos!$B$57-Supuestos!$B$52,MAX(1,ROUNDUP(G52*Supuestos!$B$49/60/Supuestos!$B$51,0)),ROUNDUP(G52*Supuestos!$B$49/60/Supuestos!$B$51,0)) | H53: =IF(H3>=Supuestos!$B$57-Supuestos!$B$52,MAX(1,ROUNDUP(H52*Supuestos!$B$49/60/Supuestos!$B$51,0)),ROUNDUP(H52*Supuestos!$B$49/60/Supuestos!$B$51,0)) | I53: =IF(I3>=Supuestos!$B$57-Supuestos!$B$52,MAX(1,ROUNDUP(I52*Supuestos!$B$49/60/Supuestos!$B$51,0)),ROUNDUP(I52*Supuestos!$B$49/60/Supuestos!$B$51,0)) | J53: =IF(J3>=Supuestos!$B$57-Supuestos!$B$52,MAX(1,ROUNDUP(J52*Supuestos!$B$49/60/Supuestos!$B$51,0)),ROUNDUP(J52*Supuestos!$B$49/60/Supuestos!$B$51,0)) | ... Z53: =IF(Z3>=Supuestos!$B$57-Supuestos!$B$52,MAX(1,ROUNDUP(Z52*Supuestos!$B$49/60/Supuestos!$B$51,0)),ROUNDUP(Z52*Supuestos!$B$49/60/Supuestos!$B$51,0))
A54: Personal de migración + capacitación | C54: =C53*Supuestos!$B$50+MAX(0,C53-0)*Supuestos!$B$53 | D54: =D53*Supuestos!$B$50+MAX(0,D53-C53)*Supuestos!$B$53 | E54: =E53*Supuestos!$B$50+MAX(0,E53-D53)*Supuestos!$B$53 | F54: =F53*Supuestos!$B$50+MAX(0,F53-E53)*Supuestos!$B$53 | G54: =G53*Supuestos!$B$50+MAX(0,G53-F53)*Supuestos!$B$53 | H54: =H53*Supuestos!$B$50+MAX(0,H53-G53)*Supuestos!$B$53 | I54: =I53*Supuestos!$B$50+MAX(0,I53-H53)*Supuestos!$B$53 | J54: =J53*Supuestos!$B$50+MAX(0,J53-I53)*Supuestos!$B$53 | K54: =K53*Supuestos!$B$50+MAX(0,K53-J53)*Supuestos!$B$53 | ... Z54: =Z53*Supuestos!$B$50+MAX(0,Z53-Y53)*Supuestos!$B$53
A55: Sueldo de Víctor | C55: =Supuestos!$B$40 | D55: =Supuestos!$B$40 | E55: =Supuestos!$B$40 | F55: =Supuestos!$B$40 | G55: =Supuestos!$B$40 | H55: =Supuestos!$B$40 | I55: =Supuestos!$B$40 | J55: =Supuestos!$B$40 | ... Z55: =Supuestos!$B$40
A56: Pagos únicos (abogado, prueba de penetración) | C56: =IF(C3=1,Supuestos!$B$41,0)+IF(C3=Supuestos!$B$43,Supuestos!$B$42,0) | D56: =IF(D3=1,Supuestos!$B$41,0)+IF(D3=Supuestos!$B$43,Supuestos!$B$42,0) | E56: =IF(E3=1,Supuestos!$B$41,0)+IF(E3=Supuestos!$B$43,Supuestos!$B$42,0) | F56: =IF(F3=1,Supuestos!$B$41,0)+IF(F3=Supuestos!$B$43,Supuestos!$B$42,0) | G56: =IF(G3=1,Supuestos!$B$41,0)+IF(G3=Supuestos!$B$43,Supuestos!$B$42,0) | H56: =IF(H3=1,Supuestos!$B$41,0)+IF(H3=Supuestos!$B$43,Supuestos!$B$42,0) | I56: =IF(I3=1,Supuestos!$B$41,0)+IF(I3=Supuestos!$B$43,Supuestos!$B$42,0) | J56: =IF(J3=1,Supuestos!$B$41,0)+IF(J3=Supuestos!$B$43,Supuestos!$B$42,0) | ... Z56: =IF(Z3=1,Supuestos!$B$41,0)+IF(Z3=Supuestos!$B$43,Supuestos!$B$42,0)
A57: Total fijos y crecimiento | C57: =C49+C50+C51+C54+C55+C56 | D57: =D49+D50+D51+D54+D55+D56 | E57: =E49+E50+E51+E54+E55+E56 | F57: =F49+F50+F51+F54+F55+F56 | G57: =G49+G50+G51+G54+G55+G56 | H57: =H49+H50+H51+H54+H55+H56 | I57: =I49+I50+I51+I54+I55+I56 | J57: =J49+J50+J51+J54+J55+J56 | ... Z57: =Z49+Z50+Z51+Z54+Z55+Z56
A59: FLUJO NETO DEL MES | C59: =C45-C57 | D59: =D45-D57 | E59: =E45-E57 | F59: =F45-F57 | G59: =G45-G57 | H59: =H45-H57 | I59: =I45-I57 | J59: =J45-J57 | ... Z59: =Z45-Z57
A60: FLUJO ACUMULADO | C60: =C59 | D60: =C60+D59 | E60: =D60+E59 | F60: =E60+F59 | G60: =F60+G59 | H60: =G60+H59 | I60: =H60+I59 | J60: =I60+J59 | K60: =J60+K59 | ... Z60: =Y60+Z59
A61: Ingreso recurrente anualizado (ARR) | C61: =C32*12 | D61: =D32*12 | E61: =E32*12 | F61: =F32*12 | G61: =G32*12 | H61: =H32*12 | I61: =I32*12 | J61: =J32*12 | ... Z61: =Z32*12
A62: Ayuda: mes con flujo positivo (99 = no) | C62: =IF(C59>0,C3,99) | D62: =IF(D59>0,D3,99) | E62: =IF(E59>0,E3,99) | F62: =IF(F59>0,F3,99) | G62: =IF(G59>0,G3,99) | H62: =IF(H59>0,H3,99) | I62: =IF(I59>0,I3,99) | J62: =IF(J59>0,J3,99) | ... Z62: =IF(Z59>0,Z3,99)

Sheet Optimista
A1: Escenario Optimista — mes a mes (MXN sin IVA)
A3: Mes # | C3: 1 | D3: 2 | E3: 3 | F3: 4 | G3: 5 | H3: 6 | I3: 7 | J3: 8 | K3: 9 | L3: 10 | M3: 11 | N3: 12 | O3: 13 | P3: 14 | Q3: 15 | R3: 16 | S3: 17 | T3: 18 | U3: 19 | V3: 20 | W3: 21 | X3: 22 | Y3: 23 | Z3: 24
A4: Mes | C4: dic-2026 | D4: ene-2027 | E4: feb-2027 | F4: mar-2027 | G4: abr-2027 | H4: may-2027 | I4: jun-2027 | J4: jul-2027 | K4: ago-2027 | L4: sep-2027 | M4: oct-2027 | N4: nov-2027 | O4: dic-2027 | P4: ene-2028 | Q4: feb-2028 | R4: mar-2028 | S4: abr-2028 | T4: may-2028 | U4: jun-2028 | V4: jul-2028 | W4: ago-2028 | X4: sep-2028 | Y4: oct-2028 | Z4: nov-2028
A5: Plan Clínico disponible (1 = sí) | C5: =IF(C3>=Supuestos!$B$43,1,0) | D5: =IF(D3>=Supuestos!$B$43,1,0) | E5: =IF(E3>=Supuestos!$B$43,1,0) | F5: =IF(F3>=Supuestos!$B$43,1,0) | G5: =IF(G3>=Supuestos!$B$43,1,0) | H5: =IF(H3>=Supuestos!$B$43,1,0) | I5: =IF(I3>=Supuestos!$B$43,1,0) | J5: =IF(J3>=Supuestos!$B$43,1,0) | ... Z5: =IF(Z3>=Supuestos!$B$43,1,0)
A7: MÉDICOS
A8: Médicos nuevos | C8: =Supuestos!$D$64 | D8: =Supuestos!$D$64 | E8: =Supuestos!$D$64 | F8: =Supuestos!$D$64 | G8: =Supuestos!$D$64 | H8: =Supuestos!$D$64 | I8: =Supuestos!$D$64 | J8: =Supuestos!$D$64 | ... Z8: =Supuestos!$D$64
A9: Fundadores nuevos | C9: =MIN(C8,Supuestos!$B$9) | D9: =MIN(D8,Supuestos!$B$9-C10) | E9: =MIN(E8,Supuestos!$B$9-D10) | F9: =MIN(F8,Supuestos!$B$9-E10) | G9: =MIN(G8,Supuestos!$B$9-F10) | H9: =MIN(H8,Supuestos!$B$9-G10) | I9: =MIN(I8,Supuestos!$B$9-H10) | J9: =MIN(J8,Supuestos!$B$9-I10) | K9: =MIN(K8,Supuestos!$B$9-J10) | ... Z9: =MIN(Z8,Supuestos!$B$9-Y10)
A10: Fundadores inscritos (acumulado) | C10: =C9 | D10: =C10+D9 | E10: =D10+E9 | F10: =E10+F9 | G10: =F10+G9 | H10: =G10+H9 | I10: =H10+I9 | J10: =I10+J9 | K10: =J10+K9 | ... Z10: =Y10+Z9
A11: Nuevos no fundadores | C11: =C8-C9 | D11: =D8-D9 | E11: =E8-E9 | F11: =F8-F9 | G11: =G8-G9 | H11: =H8-H9 | I11: =I8-I9 | J11: =J8-J9 | ... Z11: =Z8-Z9
A12: Nuevos que eligen Clínico | C12: =C11*C5*Supuestos!$D$66 | D12: =D11*D5*Supuestos!$D$66 | E12: =E11*E5*Supuestos!$D$66 | F12: =F11*F5*Supuestos!$D$66 | G12: =G11*G5*Supuestos!$D$66 | H12: =H11*H5*Supuestos!$D$66 | I12: =I11*I5*Supuestos!$D$66 | J12: =J11*J5*Supuestos!$D$66 | ... Z12: =Z11*Z5*Supuestos!$D$66
A13: Nuevos que eligen Red | C13: =C11-C12 | D13: =D11-D12 | E13: =E11-E12 | F13: =F11-F12 | G13: =G11-G12 | H13: =H11-H12 | I13: =I11-I12 | J13: =J11-J12 | ... Z13: =Z11-Z12
A14: Fundadores activos | C14: =C9 | D14: =C14*(1-Supuestos!$D$65)+D9 | E14: =D14*(1-Supuestos!$D$65)+E9 | F14: =E14*(1-Supuestos!$D$65)+F9 | G14: =F14*(1-Supuestos!$D$65)+G9 | H14: =G14*(1-Supuestos!$D$65)+H9 | I14: =H14*(1-Supuestos!$D$65)+I9 | J14: =I14*(1-Supuestos!$D$65)+J9 | K14: =J14*(1-Supuestos!$D$65)+K9 | ... Z14: =Y14*(1-Supuestos!$D$65)+Z9
A15: Suben de Red a Clínico | C15: =0 | D15: =C16*(1-Supuestos!$D$65)*D5*Supuestos!$D$67 | E15: =D16*(1-Supuestos!$D$65)*E5*Supuestos!$D$67 | F15: =E16*(1-Supuestos!$D$65)*F5*Supuestos!$D$67 | G15: =F16*(1-Supuestos!$D$65)*G5*Supuestos!$D$67 | H15: =G16*(1-Supuestos!$D$65)*H5*Supuestos!$D$67 | I15: =H16*(1-Supuestos!$D$65)*I5*Supuestos!$D$67 | J15: =I16*(1-Supuestos!$D$65)*J5*Supuestos!$D$67 | K15: =J16*(1-Supuestos!$D$65)*K5*Supuestos!$D$67 | ... Z15: =Y16*(1-Supuestos!$D$65)*Z5*Supuestos!$D$67
A16: Red activos | C16: =C13 | D16: =C16*(1-Supuestos!$D$65)-D15+D13 | E16: =D16*(1-Supuestos!$D$65)-E15+E13 | F16: =E16*(1-Supuestos!$D$65)-F15+F13 | G16: =F16*(1-Supuestos!$D$65)-G15+G13 | H16: =G16*(1-Supuestos!$D$65)-H15+H13 | I16: =H16*(1-Supuestos!$D$65)-I15+I13 | J16: =I16*(1-Supuestos!$D$65)-J15+J13 | K16: =J16*(1-Supuestos!$D$65)-K15+K13 | ... Z16: =Y16*(1-Supuestos!$D$65)-Z15+Z13
A17: Clínico activos (precio completo) | C17: =C12 | D17: =C17*(1-Supuestos!$D$65)+D12+D15 | E17: =D17*(1-Supuestos!$D$65)+E12+E15 | F17: =E17*(1-Supuestos!$D$65)+F12+F15 | G17: =F17*(1-Supuestos!$D$65)+G12+G15 | H17: =G17*(1-Supuestos!$D$65)+H12+H15 | I17: =H17*(1-Supuestos!$D$65)+I12+I15 | J17: =I17*(1-Supuestos!$D$65)+J12+J15 | K17: =J17*(1-Supuestos!$D$65)+K12+K15 | ... Z17: =Y17*(1-Supuestos!$D$65)+Z12+Z15
A18: Médicos Regene nuevos | C18: =IF(C3>=Supuestos!$B$57,Supuestos!$B$56*Supuestos!$D$69/MAX(1,25-Supuestos!$B$57),0) | D18: =IF(D3>=Supuestos!$B$57,Supuestos!$B$56*Supuestos!$D$69/MAX(1,25-Supuestos!$B$57),0) | E18: =IF(E3>=Supuestos!$B$57,Supuestos!$B$56*Supuestos!$D$69/MAX(1,25-Supuestos!$B$57),0) | F18: =IF(F3>=Supuestos!$B$57,Supuestos!$B$56*Supuestos!$D$69/MAX(1,25-Supuestos!$B$57),0) | G18: =IF(G3>=Supuestos!$B$57,Supuestos!$B$56*Supuestos!$D$69/MAX(1,25-Supuestos!$B$57),0) | H18: =IF(H3>=Supuestos!$B$57,Supuestos!$B$56*Supuestos!$D$69/MAX(1,25-Supuestos!$B$57),0) | I18: =IF(I3>=Supuestos!$B$57,Supuestos!$B$56*Supuestos!$D$69/MAX(1,25-Supuestos!$B$57),0) | J18: =IF(J3>=Supuestos!$B$57,Supuestos!$B$56*Supuestos!$D$69/MAX(1,25-Supuestos!$B$57),0) | ... Z18: =IF(Z3>=Supuestos!$B$57,Supuestos!$B$56*Supuestos!$D$69/MAX(1,25-Supuestos!$B$57),0)
A19: Médicos Regene activos (Clínico con descuento) | C19: =C18 | D19: =C19*(1-Supuestos!$D$65)+D18 | E19: =D19*(1-Supuestos!$D$65)+E18 | F19: =E19*(1-Supuestos!$D$65)+F18 | G19: =F19*(1-Supuestos!$D$65)+G18 | H19: =G19*(1-Supuestos!$D$65)+H18 | I19: =H19*(1-Supuestos!$D$65)+I18 | J19: =I19*(1-Supuestos!$D$65)+J18 | K19: =J19*(1-Supuestos!$D$65)+K18 | ... Z19: =Y19*(1-Supuestos!$D$65)+Z18
A20: Total médicos activos | C20: =C14+C16+C17+C19 | D20: =D14+D16+D17+D19 | E20: =E14+E16+E17+E19 | F20: =F14+F16+F17+F19 | G20: =G14+G16+G17+G19 | H20: =H14+H16+H17+H19 | I20: =I14+I16+I17+I19 | J20: =J14+J16+J17+J19 | ... Z20: =Z14+Z16+Z17+Z19
A21: Médicos usando el portal clínico | C21: =C17+C19+C14*C5 | D21: =D17+D19+D14*D5 | E21: =E17+E19+E14*E5 | F21: =F17+F19+F14*F5 | G21: =G17+G19+G14*G5 | H21: =H17+H19+H14*H5 | I21: =I17+I19+I14*I5 | J21: =J17+J19+J14*J5 | ... Z21: =Z17+Z19+Z14*Z5
A22: Médicos usando solo Red | C22: =C20-C21 | D22: =D20-D21 | E22: =E20-E21 | F22: =F20-F21 | G22: =G20-G21 | H22: =H20-H21 | I22: =I20-I21 | J22: =J20-J21 | ... Z22: =Z20-Z21
A24: INGRESOS
A25: Fundadores | C25: =C14*IF(C5=1,Supuestos!$B$8,Supuestos!$B$7)/(1+Supuestos!$B$10) | D25: =D14*IF(D5=1,Supuestos!$B$8,Supuestos!$B$7)/(1+Supuestos!$B$10) | E25: =E14*IF(E5=1,Supuestos!$B$8,Supuestos!$B$7)/(1+Supuestos!$B$10) | F25: =F14*IF(F5=1,Supuestos!$B$8,Supuestos!$B$7)/(1+Supuestos!$B$10) | G25: =G14*IF(G5=1,Supuestos!$B$8,Supuestos!$B$7)/(1+Supuestos!$B$10) | H25: =H14*IF(H5=1,Supuestos!$B$8,Supuestos!$B$7)/(1+Supuestos!$B$10) | I25: =I14*IF(I5=1,Supuestos!$B$8,Supuestos!$B$7)/(1+Supuestos!$B$10) | J25: =J14*IF(J5=1,Supuestos!$B$8,Supuestos!$B$7)/(1+Supuestos!$B$10) | ... Z25: =Z14*IF(Z5=1,Supuestos!$B$8,Supuestos!$B$7)/(1+Supuestos!$B$10)
A26: Plan Red | C26: =C16*Supuestos!$B$5/(1+Supuestos!$B$10) | D26: =D16*Supuestos!$B$5/(1+Supuestos!$B$10) | E26: =E16*Supuestos!$B$5/(1+Supuestos!$B$10) | F26: =F16*Supuestos!$B$5/(1+Supuestos!$B$10) | G26: =G16*Supuestos!$B$5/(1+Supuestos!$B$10) | H26: =H16*Supuestos!$B$5/(1+Supuestos!$B$10) | I26: =I16*Supuestos!$B$5/(1+Supuestos!$B$10) | J26: =J16*Supuestos!$B$5/(1+Supuestos!$B$10) | ... Z26: =Z16*Supuestos!$B$5/(1+Supuestos!$B$10)
A27: Plan Clínico | C27: =C17*Supuestos!$B$6/(1+Supuestos!$B$10) | D27: =D17*Supuestos!$B$6/(1+Supuestos!$B$10) | E27: =E17*Supuestos!$B$6/(1+Supuestos!$B$10) | F27: =F17*Supuestos!$B$6/(1+Supuestos!$B$10) | G27: =G17*Supuestos!$B$6/(1+Supuestos!$B$10) | H27: =H17*Supuestos!$B$6/(1+Supuestos!$B$10) | I27: =I17*Supuestos!$B$6/(1+Supuestos!$B$10) | J27: =J17*Supuestos!$B$6/(1+Supuestos!$B$10) | ... Z27: =Z17*Supuestos!$B$6/(1+Supuestos!$B$10)
A28: Canal Regene | C28: =C19*Supuestos!$B$6*(1-Supuestos!$B$58)/(1+Supuestos!$B$10) | D28: =D19*Supuestos!$B$6*(1-Supuestos!$B$58)/(1+Supuestos!$B$10) | E28: =E19*Supuestos!$B$6*(1-Supuestos!$B$58)/(1+Supuestos!$B$10) | F28: =F19*Supuestos!$B$6*(1-Supuestos!$B$58)/(1+Supuestos!$B$10) | G28: =G19*Supuestos!$B$6*(1-Supuestos!$B$58)/(1+Supuestos!$B$10) | H28: =H19*Supuestos!$B$6*(1-Supuestos!$B$58)/(1+Supuestos!$B$10) | I28: =I19*Supuestos!$B$6*(1-Supuestos!$B$58)/(1+Supuestos!$B$10) | J28: =J19*Supuestos!$B$6*(1-Supuestos!$B$58)/(1+Supuestos!$B$10) | ... Z28: =Z19*Supuestos!$B$6*(1-Supuestos!$B$58)/(1+Supuestos!$B$10)
A29: GB adicionales cobrados (médicos de alto consumo) | C29: =C21*Supuestos!$B$25*Supuestos!$B$26 | D29: =D21*Supuestos!$B$25*Supuestos!$B$26 | E29: =E21*Supuestos!$B$25*Supuestos!$B$26 | F29: =F21*Supuestos!$B$25*Supuestos!$B$26 | G29: =G21*Supuestos!$B$25*Supuestos!$B$26 | H29: =H21*Supuestos!$B$25*Supuestos!$B$26 | I29: =I21*Supuestos!$B$25*Supuestos!$B$26 | J29: =J21*Supuestos!$B$25*Supuestos!$B$26 | ... Z29: =Z21*Supuestos!$B$25*Supuestos!$B$26
A30: GB guardados en total (se conservan 5 años, NOM-004) | C30: =C21*Supuestos!$B$24+C29 | D30: =C30-C29+D21*Supuestos!$B$24+D29 | E30: =D30-D29+E21*Supuestos!$B$24+E29 | F30: =E30-E29+F21*Supuestos!$B$24+F29 | G30: =F30-F29+G21*Supuestos!$B$24+G29 | H30: =G30-G29+H21*Supuestos!$B$24+H29 | I30: =H30-H29+I21*Supuestos!$B$24+I29 | J30: =I30-I29+J21*Supuestos!$B$24+J29 | K30: =J30-J29+K21*Supuestos!$B$24+K29 | ... Z30: =Y30-Y29+Z21*Supuestos!$B$24+Z29
A31: Almacenamiento adicional | C31: =C29*Supuestos!$B$23/(1+Supuestos!$B$10) | D31: =D29*Supuestos!$B$23/(1+Supuestos!$B$10) | E31: =E29*Supuestos!$B$23/(1+Supuestos!$B$10) | F31: =F29*Supuestos!$B$23/(1+Supuestos!$B$10) | G31: =G29*Supuestos!$B$23/(1+Supuestos!$B$10) | H31: =H29*Supuestos!$B$23/(1+Supuestos!$B$10) | I31: =I29*Supuestos!$B$23/(1+Supuestos!$B$10) | J31: =J29*Supuestos!$B$23/(1+Supuestos!$B$10) | ... Z31: =Z29*Supuestos!$B$23/(1+Supuestos!$B$10)
A32: Ingreso recurrente mensual (MRR) | C32: =C25+C26+C27+C28+C31 | D32: =D25+D26+D27+D28+D31 | E32: =E25+E26+E27+E28+E31 | F32: =F25+F26+F27+F28+F31 | G32: =G25+G26+G27+G28+G31 | H32: =H25+H26+H27+H28+H31 | I32: =I25+I26+I27+I28+I31 | J32: =J25+J26+J27+J28+J31 | ... Z32: =Z25+Z26+Z27+Z28+Z31
A33: Migraciones vendidas | C33: =(C12+C15+C18)*Supuestos!$D$68 | D33: =(D12+D15+D18)*Supuestos!$D$68 | E33: =(E12+E15+E18)*Supuestos!$D$68 | F33: =(F12+F15+F18)*Supuestos!$D$68 | G33: =(G12+G15+G18)*Supuestos!$D$68 | H33: =(H12+H15+H18)*Supuestos!$D$68 | I33: =(I12+I15+I18)*Supuestos!$D$68 | J33: =(J12+J15+J18)*Supuestos!$D$68 | ... Z33: =(Z12+Z15+Z18)*Supuestos!$D$68
A34: Ingreso por migraciones | C34: =C33*Supuestos!$B$46*Supuestos!$B$11/(1+Supuestos!$B$10) | D34: =D33*Supuestos!$B$46*Supuestos!$B$11/(1+Supuestos!$B$10) | E34: =E33*Supuestos!$B$46*Supuestos!$B$11/(1+Supuestos!$B$10) | F34: =F33*Supuestos!$B$46*Supuestos!$B$11/(1+Supuestos!$B$10) | G34: =G33*Supuestos!$B$46*Supuestos!$B$11/(1+Supuestos!$B$10) | H34: =H33*Supuestos!$B$46*Supuestos!$B$11/(1+Supuestos!$B$10) | I34: =I33*Supuestos!$B$46*Supuestos!$B$11/(1+Supuestos!$B$10) | J34: =J33*Supuestos!$B$46*Supuestos!$B$11/(1+Supuestos!$B$10) | ... Z34: =Z33*Supuestos!$B$46*Supuestos!$B$11/(1+Supuestos!$B$10)
A35: INGRESO TOTAL | C35: =C32+C34 | D35: =D32+D34 | E35: =E32+E34 | F35: =F32+F34 | G35: =G32+G34 | H35: =H32+H34 | I35: =I32+I34 | J35: =J32+J34 | ... Z35: =Z32+Z34
A37: COSTOS VARIABLES
A38: IA (NOVA) | C38: =(C22*Supuestos!$B$17+C21*Supuestos!$B$18)*Supuestos!$B$14 | D38: =(D22*Supuestos!$B$17+D21*Supuestos!$B$18)*Supuestos!$B$14 | E38: =(E22*Supuestos!$B$17+E21*Supuestos!$B$18)*Supuestos!$B$14 | F38: =(F22*Supuestos!$B$17+F21*Supuestos!$B$18)*Supuestos!$B$14 | G38: =(G22*Supuestos!$B$17+G21*Supuestos!$B$18)*Supuestos!$B$14 | H38: =(H22*Supuestos!$B$17+H21*Supuestos!$B$18)*Supuestos!$B$14 | I38: =(I22*Supuestos!$B$17+I21*Supuestos!$B$18)*Supuestos!$B$14 | J38: =(J22*Supuestos!$B$17+J21*Supuestos!$B$18)*Supuestos!$B$14 | ... Z38: =(Z22*Supuestos!$B$17+Z21*Supuestos!$B$18)*Supuestos!$B$14
A39: Almacenamiento (2 copias) | C39: =C30*(Supuestos!$B$27+Supuestos!$B$28)*Supuestos!$B$14 | D39: =D30*(Supuestos!$B$27+Supuestos!$B$28)*Supuestos!$B$14 | E39: =E30*(Supuestos!$B$27+Supuestos!$B$28)*Supuestos!$B$14 | F39: =F30*(Supuestos!$B$27+Supuestos!$B$28)*Supuestos!$B$14 | G39: =G30*(Supuestos!$B$27+Supuestos!$B$28)*Supuestos!$B$14 | H39: =H30*(Supuestos!$B$27+Supuestos!$B$28)*Supuestos!$B$14 | I39: =I30*(Supuestos!$B$27+Supuestos!$B$28)*Supuestos!$B$14 | J39: =J30*(Supuestos!$B$27+Supuestos!$B$28)*Supuestos!$B$14 | ... Z39: =Z30*(Supuestos!$B$27+Supuestos!$B$28)*Supuestos!$B$14
A40: Comisión de cobro (con IVA de la comisión) | C40: =((C20+C33)*Supuestos!$B$32+C35*(1+Supuestos!$B$10)*Supuestos!$B$31)*(1+Supuestos!$B$10) | D40: =((D20+D33)*Supuestos!$B$32+D35*(1+Supuestos!$B$10)*Supuestos!$B$31)*(1+Supuestos!$B$10) | E40: =((E20+E33)*Supuestos!$B$32+E35*(1+Supuestos!$B$10)*Supuestos!$B$31)*(1+Supuestos!$B$10) | F40: =((F20+F33)*Supuestos!$B$32+F35*(1+Supuestos!$B$10)*Supuestos!$B$31)*(1+Supuestos!$B$10) | G40: =((G20+G33)*Supuestos!$B$32+G35*(1+Supuestos!$B$10)*Supuestos!$B$31)*(1+Supuestos!$B$10) | H40: =((H20+H33)*Supuestos!$B$32+H35*(1+Supuestos!$B$10)*Supuestos!$B$31)*(1+Supuestos!$B$10) | I40: =((I20+I33)*Supuestos!$B$32+I35*(1+Supuestos!$B$10)*Supuestos!$B$31)*(1+Supuestos!$B$10) | J40: =((J20+J33)*Supuestos!$B$32+J35*(1+Supuestos!$B$10)*Supuestos!$B$31)*(1+Supuestos!$B$10) | ... Z40: =((Z20+Z33)*Supuestos!$B$32+Z35*(1+Supuestos!$B$10)*Supuestos!$B$31)*(1+Supuestos!$B$10)
A41: Facturas CFDI | C41: =(C20+C33)*Supuestos!$B$33 | D41: =(D20+D33)*Supuestos!$B$33 | E41: =(E20+E33)*Supuestos!$B$33 | F41: =(F20+F33)*Supuestos!$B$33 | G41: =(G20+G33)*Supuestos!$B$33 | H41: =(H20+H33)*Supuestos!$B$33 | I41: =(I20+I33)*Supuestos!$B$33 | J41: =(J20+J33)*Supuestos!$B$33 | ... Z41: =(Z20+Z33)*Supuestos!$B$33
A42: Soporte | C42: =C20*Supuestos!$B$37*Supuestos!$B$38 | D42: =D20*Supuestos!$B$37*Supuestos!$B$38 | E42: =E20*Supuestos!$B$37*Supuestos!$B$38 | F42: =F20*Supuestos!$B$37*Supuestos!$B$38 | G42: =G20*Supuestos!$B$37*Supuestos!$B$38 | H42: =H20*Supuestos!$B$37*Supuestos!$B$38 | I42: =I20*Supuestos!$B$37*Supuestos!$B$38 | J42: =J20*Supuestos!$B$37*Supuestos!$B$38 | ... Z42: =Z20*Supuestos!$B$37*Supuestos!$B$38
A43: IA de las migraciones | C43: =C33*Supuestos!$B$46*Supuestos!$B$47*Supuestos!$B$48*Supuestos!$B$14 | D43: =D33*Supuestos!$B$46*Supuestos!$B$47*Supuestos!$B$48*Supuestos!$B$14 | E43: =E33*Supuestos!$B$46*Supuestos!$B$47*Supuestos!$B$48*Supuestos!$B$14 | F43: =F33*Supuestos!$B$46*Supuestos!$B$47*Supuestos!$B$48*Supuestos!$B$14 | G43: =G33*Supuestos!$B$46*Supuestos!$B$47*Supuestos!$B$48*Supuestos!$B$14 | H43: =H33*Supuestos!$B$46*Supuestos!$B$47*Supuestos!$B$48*Supuestos!$B$14 | I43: =I33*Supuestos!$B$46*Supuestos!$B$47*Supuestos!$B$48*Supuestos!$B$14 | J43: =J33*Supuestos!$B$46*Supuestos!$B$47*Supuestos!$B$48*Supuestos!$B$14 | ... Z43: =Z33*Supuestos!$B$46*Supuestos!$B$47*Supuestos!$B$48*Supuestos!$B$14
A44: Total costos variables | C44: =SUM(C38:C43) | D44: =SUM(D38:D43) | E44: =SUM(E38:E43) | F44: =SUM(F38:F43) | G44: =SUM(G38:G43) | H44: =SUM(H38:H43) | I44: =SUM(I38:I43) | J44: =SUM(J38:J43) | ... Z44: =SUM(Z38:Z43)
A45: MARGEN DE CONTRIBUCIÓN | C45: =C35-C44 | D45: =D35-D44 | E45: =E35-E44 | F45: =F35-F44 | G45: =G35-G44 | H45: =H35-H44 | I45: =I35-I44 | J45: =J35-J44 | ... Z45: =Z35-Z44
A46: Margen de contribución % | C46: =IF(C35=0,0,C45/C35) | D46: =IF(D35=0,0,D45/D35) | E46: =IF(E35=0,0,E45/E35) | F46: =IF(F35=0,0,F45/F35) | G46: =IF(G35=0,0,G45/G35) | H46: =IF(H35=0,0,H45/H35) | I46: =IF(I35=0,0,I45/I35) | J46: =IF(J35=0,0,J45/J35) | ... Z46: =IF(Z35=0,0,Z45/Z35)
A48: COSTOS FIJOS Y DE CRECIMIENTO
A49: Infraestructura | C49: =(Supuestos!$B$15+Supuestos!$B$16*C5+Supuestos!$B$61*INT(C20/100)+IF(C3>=Supuestos!$B$57-1,Supuestos!$B$59,0))*Supuestos!$B$14 | D49: =(Supuestos!$B$15+Supuestos!$B$16*D5+Supuestos!$B$61*INT(D20/100)+IF(D3>=Supuestos!$B$57-1,Supuestos!$B$59,0))*Supuestos!$B$14 | E49: =(Supuestos!$B$15+Supuestos!$B$16*E5+Supuestos!$B$61*INT(E20/100)+IF(E3>=Supuestos!$B$57-1,Supuestos!$B$59,0))*Supuestos!$B$14 | F49: =(Supuestos!$B$15+Supuestos!$B$16*F5+Supuestos!$B$61*INT(F20/100)+IF(F3>=Supuestos!$B$57-1,Supuestos!$B$59,0))*Supuestos!$B$14 | G49: =(Supuestos!$B$15+Supuestos!$B$16*G5+Supuestos!$B$61*INT(G20/100)+IF(G3>=Supuestos!$B$57-1,Supuestos!$B$59,0))*Supuestos!$B$14 | H49: =(Supuestos!$B$15+Supuestos!$B$16*H5+Supuestos!$B$61*INT(H20/100)+IF(H3>=Supuestos!$B$57-1,Supuestos!$B$59,0))*Supuestos!$B$14 | I49: =(Supuestos!$B$15+Supuestos!$B$16*I5+Supuestos!$B$61*INT(I20/100)+IF(I3>=Supuestos!$B$57-1,Supuestos!$B$59,0))*Supuestos!$B$14 | J49: =(Supuestos!$B$15+Supuestos!$B$16*J5+Supuestos!$B$61*INT(J20/100)+IF(J3>=Supuestos!$B$57-1,Supuestos!$B$59,0))*Supuestos!$B$14 | ... Z49: =(Supuestos!$B$15+Supuestos!$B$16*Z5+Supuestos!$B$61*INT(Z20/100)+IF(Z3>=Supuestos!$B$57-1,Supuestos!$B$59,0))*Supuestos!$B$14
A50: Contador | C50: =Supuestos!$B$36 | D50: =Supuestos!$B$36 | E50: =Supuestos!$B$36 | F50: =Supuestos!$B$36 | G50: =Supuestos!$B$36 | H50: =Supuestos!$B$36 | I50: =Supuestos!$B$36 | J50: =Supuestos!$B$36 | ... Z50: =Supuestos!$B$36
A51: Adquisición de médicos | C51: =C8*Supuestos!$B$39+C18*Supuestos!$B$60 | D51: =D8*Supuestos!$B$39+D18*Supuestos!$B$60 | E51: =E8*Supuestos!$B$39+E18*Supuestos!$B$60 | F51: =F8*Supuestos!$B$39+F18*Supuestos!$B$60 | G51: =G8*Supuestos!$B$39+G18*Supuestos!$B$60 | H51: =H8*Supuestos!$B$39+H18*Supuestos!$B$60 | I51: =I8*Supuestos!$B$39+I18*Supuestos!$B$60 | J51: =J8*Supuestos!$B$39+J18*Supuestos!$B$60 | ... Z51: =Z8*Supuestos!$B$39+Z18*Supuestos!$B$60
A52: Páginas a revisar (migración asistida) | C52: =C33*Supuestos!$B$46*Supuestos!$B$47 | D52: =D33*Supuestos!$B$46*Supuestos!$B$47 | E52: =E33*Supuestos!$B$46*Supuestos!$B$47 | F52: =F33*Supuestos!$B$46*Supuestos!$B$47 | G52: =G33*Supuestos!$B$46*Supuestos!$B$47 | H52: =H33*Supuestos!$B$46*Supuestos!$B$47 | I52: =I33*Supuestos!$B$46*Supuestos!$B$47 | J52: =J33*Supuestos!$B$46*Supuestos!$B$47 | ... Z52: =Z33*Supuestos!$B$46*Supuestos!$B$47
A53: Personas de migración | C53: =IF(C3>=Supuestos!$B$57-Supuestos!$B$52,MAX(1,ROUNDUP(C52*Supuestos!$B$49/60/Supuestos!$B$51,0)),ROUNDUP(C52*Supuestos!$B$49/60/Supuestos!$B$51,0)) | D53: =IF(D3>=Supuestos!$B$57-Supuestos!$B$52,MAX(1,ROUNDUP(D52*Supuestos!$B$49/60/Supuestos!$B$51,0)),ROUNDUP(D52*Supuestos!$B$49/60/Supuestos!$B$51,0)) | E53: =IF(E3>=Supuestos!$B$57-Supuestos!$B$52,MAX(1,ROUNDUP(E52*Supuestos!$B$49/60/Supuestos!$B$51,0)),ROUNDUP(E52*Supuestos!$B$49/60/Supuestos!$B$51,0)) | F53: =IF(F3>=Supuestos!$B$57-Supuestos!$B$52,MAX(1,ROUNDUP(F52*Supuestos!$B$49/60/Supuestos!$B$51,0)),ROUNDUP(F52*Supuestos!$B$49/60/Supuestos!$B$51,0)) | G53: =IF(G3>=Supuestos!$B$57-Supuestos!$B$52,MAX(1,ROUNDUP(G52*Supuestos!$B$49/60/Supuestos!$B$51,0)),ROUNDUP(G52*Supuestos!$B$49/60/Supuestos!$B$51,0)) | H53: =IF(H3>=Supuestos!$B$57-Supuestos!$B$52,MAX(1,ROUNDUP(H52*Supuestos!$B$49/60/Supuestos!$B$51,0)),ROUNDUP(H52*Supuestos!$B$49/60/Supuestos!$B$51,0)) | I53: =IF(I3>=Supuestos!$B$57-Supuestos!$B$52,MAX(1,ROUNDUP(I52*Supuestos!$B$49/60/Supuestos!$B$51,0)),ROUNDUP(I52*Supuestos!$B$49/60/Supuestos!$B$51,0)) | J53: =IF(J3>=Supuestos!$B$57-Supuestos!$B$52,MAX(1,ROUNDUP(J52*Supuestos!$B$49/60/Supuestos!$B$51,0)),ROUNDUP(J52*Supuestos!$B$49/60/Supuestos!$B$51,0)) | ... Z53: =IF(Z3>=Supuestos!$B$57-Supuestos!$B$52,MAX(1,ROUNDUP(Z52*Supuestos!$B$49/60/Supuestos!$B$51,0)),ROUNDUP(Z52*Supuestos!$B$49/60/Supuestos!$B$51,0))
A54: Personal de migración + capacitación | C54: =C53*Supuestos!$B$50+MAX(0,C53-0)*Supuestos!$B$53 | D54: =D53*Supuestos!$B$50+MAX(0,D53-C53)*Supuestos!$B$53 | E54: =E53*Supuestos!$B$50+MAX(0,E53-D53)*Supuestos!$B$53 | F54: =F53*Supuestos!$B$50+MAX(0,F53-E53)*Supuestos!$B$53 | G54: =G53*Supuestos!$B$50+MAX(0,G53-F53)*Supuestos!$B$53 | H54: =H53*Supuestos!$B$50+MAX(0,H53-G53)*Supuestos!$B$53 | I54: =I53*Supuestos!$B$50+MAX(0,I53-H53)*Supuestos!$B$53 | J54: =J53*Supuestos!$B$50+MAX(0,J53-I53)*Supuestos!$B$53 | K54: =K53*Supuestos!$B$50+MAX(0,K53-J53)*Supuestos!$B$53 | ... Z54: =Z53*Supuestos!$B$50+MAX(0,Z53-Y53)*Supuestos!$B$53
A55: Sueldo de Víctor | C55: =Supuestos!$B$40 | D55: =Supuestos!$B$40 | E55: =Supuestos!$B$40 | F55: =Supuestos!$B$40 | G55: =Supuestos!$B$40 | H55: =Supuestos!$B$40 | I55: =Supuestos!$B$40 | J55: =Supuestos!$B$40 | ... Z55: =Supuestos!$B$40
A56: Pagos únicos (abogado, prueba de penetración) | C56: =IF(C3=1,Supuestos!$B$41,0)+IF(C3=Supuestos!$B$43,Supuestos!$B$42,0) | D56: =IF(D3=1,Supuestos!$B$41,0)+IF(D3=Supuestos!$B$43,Supuestos!$B$42,0) | E56: =IF(E3=1,Supuestos!$B$41,0)+IF(E3=Supuestos!$B$43,Supuestos!$B$42,0) | F56: =IF(F3=1,Supuestos!$B$41,0)+IF(F3=Supuestos!$B$43,Supuestos!$B$42,0) | G56: =IF(G3=1,Supuestos!$B$41,0)+IF(G3=Supuestos!$B$43,Supuestos!$B$42,0) | H56: =IF(H3=1,Supuestos!$B$41,0)+IF(H3=Supuestos!$B$43,Supuestos!$B$42,0) | I56: =IF(I3=1,Supuestos!$B$41,0)+IF(I3=Supuestos!$B$43,Supuestos!$B$42,0) | J56: =IF(J3=1,Supuestos!$B$41,0)+IF(J3=Supuestos!$B$43,Supuestos!$B$42,0) | ... Z56: =IF(Z3=1,Supuestos!$B$41,0)+IF(Z3=Supuestos!$B$43,Supuestos!$B$42,0)
A57: Total fijos y crecimiento | C57: =C49+C50+C51+C54+C55+C56 | D57: =D49+D50+D51+D54+D55+D56 | E57: =E49+E50+E51+E54+E55+E56 | F57: =F49+F50+F51+F54+F55+F56 | G57: =G49+G50+G51+G54+G55+G56 | H57: =H49+H50+H51+H54+H55+H56 | I57: =I49+I50+I51+I54+I55+I56 | J57: =J49+J50+J51+J54+J55+J56 | ... Z57: =Z49+Z50+Z51+Z54+Z55+Z56
A59: FLUJO NETO DEL MES | C59: =C45-C57 | D59: =D45-D57 | E59: =E45-E57 | F59: =F45-F57 | G59: =G45-G57 | H59: =H45-H57 | I59: =I45-I57 | J59: =J45-J57 | ... Z59: =Z45-Z57
A60: FLUJO ACUMULADO | C60: =C59 | D60: =C60+D59 | E60: =D60+E59 | F60: =E60+F59 | G60: =F60+G59 | H60: =G60+H59 | I60: =H60+I59 | J60: =I60+J59 | K60: =J60+K59 | ... Z60: =Y60+Z59
A61: Ingreso recurrente anualizado (ARR) | C61: =C32*12 | D61: =D32*12 | E61: =E32*12 | F61: =F32*12 | G61: =G32*12 | H61: =H32*12 | I61: =I32*12 | J61: =J32*12 | ... Z61: =Z32*12
A62: Ayuda: mes con flujo positivo (99 = no) | C62: =IF(C59>0,C3,99) | D62: =IF(D59>0,D3,99) | E62: =IF(E59>0,E3,99) | F62: =IF(F59>0,F3,99) | G62: =IF(G59>0,G3,99) | H62: =IF(H59>0,H3,99) | I62: =IF(I59>0,I3,99) | J62: =IF(J59>0,J3,99) | ... Z62: =IF(Z59>0,Z3,99)
